Workbook
Name in_mode_sale: Assumptions!$B$8
Name in_ground_up: Assumptions!$B$9
Name in_circ_switch: Assumptions!$B$10
Name in_site_land_area: Assumptions!$B$12
Name in_site_land_price: Assumptions!$B$13
Name in_site_transfer_tax_pct: Assumptions!$B$14
Name in_site_legal_notary_pct: Assumptions!$B$15
Name in_site_brokerage_pct: Assumptions!$B$16
Name in_site_due_diligence: Assumptions!$B$17
Name in_reg_max_stories: Assumptions!$B$19
Name in_reg_min_open_area_pct: Assumptions!$B$20
Name in_reg_max_far: Assumptions!$B$21
Name in_reg_max_height_m: Assumptions!$B$22
Name in_reg_min_land_per_unit: Assumptions!$B$23
Name in_reg_max_units: Assumptions!$B$24
Name in_reg_max_underground_levels: Assumptions!$B$25
Name in_reg_parking_min_per_unit: Assumptions!$B$26
Name in_reg_parking_max_per_unit: Assumptions!$B$27
Name in_dev_buildings: Assumptions!$B$29
Name in_dev_stories: Assumptions!$B$30
Name in_dev_levels_below: Assumptions!$B$31
Name in_dev_footprint: Assumptions!$B$32
Name in_dev_efficiency_pct: Assumptions!$B$33
Name in_dev_parking_spaces: Assumptions!$B$34
Name in_dev_parking_area_per_space: Assumptions!$B$35
Name in_dev_amenity_area: Assumptions!$B$36
Name in_dev_quality: Assumptions!$B$37
Name in_dev_existing_rentable_area: Assumptions!$B$38
Name in_rev_price_per_area: Assumptions!$B$40
Name in_rev_floor_view_premium_pct: Assumptions!$B$41
Name in_rev_terrace_value_pct: Assumptions!$B$42
Name in_rev_discount_pct: Assumptions!$B$43
Name in_rev_escalation_pct: Assumptions!$B$44
Name in_rev_absorption_per_month: Assumptions!$B$45
Name in_rev_cancellation_pct: Assumptions!$B$46
Name in_rev_sales_start_offset: Assumptions!$B$47
Name in_rev_deposit_pct: Assumptions!$B$48
Name in_rev_installments_pct: Assumptions!$B$49
Name in_rev_closing_pct: Assumptions!$B$50
Name in_rev_commission_pct: Assumptions!$B$51
Name in_rev_marketing_pct: Assumptions!$B$52
Name in_rent_rent_per_area_month: Assumptions!$B$54
Name in_rent_vacancy_pct: Assumptions!$B$55
Name in_rent_concessions_pct: Assumptions!$B$56
Name in_rent_opex_pct_egi: Assumptions!$B$57
Name in_rent_growth_pct: Assumptions!$B$58
Name in_rent_lease_up_months: Assumptions!$B$59
Name in_rent_exit_cap_pct: Assumptions!$B$60
Name in_rent_selling_costs_pct: Assumptions!$B$61
Name in_rent_hold_years: Assumptions!$B$62
Name in_cost_hard_per_area: Assumptions!$B$64
Name in_cost_below_grade_per_area: Assumptions!$B$65
Name in_cost_demolition: Assumptions!$B$66
Name in_cost_infrastructure_fees: Assumptions!$B$67
Name in_cost_renovation_budget: Assumptions!$B$68
Name in_cost_design_pct: Assumptions!$B$69
Name in_cost_permits_pct: Assumptions!$B$70
Name in_cost_pm_supervision_pct: Assumptions!$B$71
Name in_cost_insurance_other_pct: Assumptions!$B$72
Name in_cost_contingency_pct: Assumptions!$B$73

Sheet Cover
B2: TerraMind AI · Financial model
B3: Polanco Residences (fictional)
B5: Location | C5: Fictional lot near Calle Lope de Vega, Polanco, Miguel Hidalgo, Polanco V Sección, Mexico City
B6: Strategy / business model | C6: ground_up · build_to_sell
B7: Currency | C7: MXN
B8: Exported | C8: 2026-10-24
B9: How it works | C9: Change any blue cell on the Assumptions tab. Every other number is a formula, so the development program, schedules, cash flow, financing, waterfall, budget, outputs and charts all update.
B10: Circularity | C10: Debt is sized on total cost including financing, which is circular. Iterative calculation is enabled in this file (File → Options → Formulas → Enable iterative calculation).
B11: Reconciliation | C11: The Outputs tab compares the Excel results with TerraMind's engine at the time of export.
B12: Disclaimer | C12: FICTIONAL DEMO PROJECT: all inputs are illustrative. Decision support only, not investment advice. Verify assumptions before relying on them.
B14: Tabs
B15: Outputs | C15: Returns, profit, capital, reconciliation, annual summary and charts for investors
B16: Assumptions | C16: Every input (blue), unit mix, schedules, custom cash flows, user-defined variables
B17: Development | C17: Areas, units, legal capacity and compliance checks
B18: Construction | C18: Monthly development cost schedule (S-curve, escalation, land payments)
B19: Sales | C19: Monthly sales and buyer payments
B20: Cash Flow | C20: Unlevered cash flow, debt draws and repayments, interest, equity
B21: Waterfall | C21: Investor vs sponsor distributions
B22: Budget | C22: Development budget by line item
B23: Sensitivity | C23: Scenario, tornado and heatmap results from TerraMind's engine (snapshot)
B25: Legend
B26: 1,234 | C26: Input (edit these)
B27: 1,234 | C27: Formula (do not overwrite)
B28: Key driver | C28: Most important inputs

Sheet Outputs
A1: Polanco Residences (fictional): investment summary
A2: MXN. Every figure is a formula linked to the Assumptions tab.
A4: Metric | B4: Excel model | C4: TerraMind engine at export | D4: Difference | E4: Status
A5: Returns
A6: Project IRR (unlevered, annualized) | B6: =IFERROR((1+IRR(M_Unlev,0.01))^12-1,"n/a") | C6: 0.25173236 | D6: =IFERROR(B6-C6,"") | E6: =IFERROR(IF(IF(ABS(C6)<10,ABS(B6-C6)<=0.0005,ABS(B6-C6)<=MAX(1,ABS(C6)*0.002)),"✓ matches","changed"),"")
A7: Equity IRR (levered, annualized) | B7: =IFERROR((1+IRR(M_Lev,0.01))^12-1,"n/a") | C7: 0.24913765 | D7: =IFERROR(B7-C7,"") | E7: =IFERROR(IF(IF(ABS(C7)<10,ABS(B7-C7)<=0.0005,ABS(B7-C7)<=MAX(1,ABS(C7)*0.002)),"✓ matches","changed"),"")
A8: Equity multiple (MOIC) | B8: =IF(SUM(M_Contrib)>0,SUM(M_Dist)/SUM(M_Contrib),0) | C8: 1.6770593 | D8: =IFERROR(B8-C8,"") | E8: =IFERROR(IF(IF(ABS(C8)<10,ABS(B8-C8)<=0.0005,ABS(B8-C8)<=MAX(1,ABS(C8)*0.002)),"✓ matches","changed"),"")
A9: NPV at discount rate (unlevered) | B9: =INDEX(M_Unlev,1,1)+NPV((1+in_val_discount_rate_pct)^(1/12)-1,'Cash Flow'!$E$26:$CU$26) | C9: 1.2245185e+08 | D9: =IFERROR(B9-C9,"") | E9: =IFERROR(IF(IF(ABS(C9)<10,ABS(B9-C9)<=0.0005,ABS(B9-C9)<=MAX(1,ABS(C9)*0.002)),"✓ matches","changed"),"")
A10: Investor IRR | B10: =IFERROR((1+IRR(M_Investor,0.01))^12-1,"n/a") | C10: 0.22143822 | D10: =IFERROR(B10-C10,"") | E10: =IFERROR(IF(IF(ABS(C10)<10,ABS(B10-C10)<=0.0005,ABS(B10-C10)<=MAX(1,ABS(C10)*0.002)),"✓ matches","changed"),"")
A11: Sponsor IRR | B11: =IFERROR((1+IRR(M_Sponsor,0.01))^12-1,"n/a") | C11: 0.3517446 | D11: =IFERROR(B11-C11,"") | E11: =IFERROR(IF(IF(ABS(C11)<10,ABS(B11-C11)<=0.0005,ABS(B11-C11)<=MAX(1,ABS(C11)*0.002)),"✓ matches","changed"),"")
A12: Profitability
A13: Gross development value / exit value | B13: =IF(in_mode_sale=1,S_GDV,R_ExitValue) | C13: 1.0364814e+09 | D13: =IFERROR(B13-C13,"") | E13: =IFERROR(IF(IF(ABS(C13)<10,ABS(B13-C13)<=0.0005,ABS(B13-C13)<=MAX(1,ABS(C13)*0.002)),"✓ matches","changed"),"")
A14: Total revenue (cash inflows) | B14: =SUM(M_Inflow) | C14: 1.0364814e+09 | D14: =IFERROR(B14-C14,"") | E14: =IFERROR(IF(IF(ABS(C14)<10,ABS(B14-C14)<=0.0005,ABS(B14-C14)<=MAX(1,ABS(C14)*0.002)),"✓ matches","changed"),"")
A15: Total development cost (excl. financing) | B15: =TDC | C15: 7.4189385e+08 | D15: =IFERROR(B15-C15,"") | E15: =IFERROR(IF(IF(ABS(C15)<10,ABS(B15-C15)<=0.0005,ABS(B15-C15)<=MAX(1,ABS(C15)*0.002)),"✓ matches","changed"),"")
A16: Financing cost | B16: =FinCost | C16: 13348403 | D16: =IFERROR(B16-C16,"") | E16: =IFERROR(IF(IF(ABS(C16)<10,ABS(B16-C16)<=0.0005,ABS(B16-C16)<=MAX(1,ABS(C16)*0.002)),"✓ matches","changed"),"")
A17: Total cost incl. financing | B17: =TotalCost | C17: 7.5524226e+08 | D17: =IFERROR(B17-C17,"") | E17: =IFERROR(IF(IF(ABS(C17)<10,ABS(B17-C17)<=0.0005,ABS(B17-C17)<=MAX(1,ABS(C17)*0.002)),"✓ matches","changed"),"")
A18: Development profit | B18: =SUM(M_Inflow)-TotalCost | C18: 2.812391e+08 | D18: =IFERROR(B18-C18,"") | E18: =IFERROR(IF(IF(ABS(C18)<10,ABS(B18-C18)<=0.0005,ABS(B18-C18)<=MAX(1,ABS(C18)*0.002)),"✓ matches","changed"),"")
A19: Net margin (profit / revenue) | B19: =IF(SUM(M_Inflow)<>0,(SUM(M_Inflow)-TotalCost)/SUM(M_Inflow),0) | C19: 0.27134024 | D19: =IFERROR(B19-C19,"") | E19: =IFERROR(IF(IF(ABS(C19)<10,ABS(B19-C19)<=0.0005,ABS(B19-C19)<=MAX(1,ABS(C19)*0.002)),"✓ matches","changed"),"")
A20: Profit on cost | B20: =IF(TotalCost<>0,(SUM(M_Inflow)-TotalCost)/TotalCost,0) | C20: 0.37238263 | D20: =IFERROR(B20-C20,"") | E20: =IFERROR(IF(IF(ABS(C20)<10,ABS(B20-C20)<=0.0005,ABS(B20-C20)<=MAX(1,ABS(C20)*0.002)),"✓ matches","changed"),"")
A21: Capital
A22: Peak funding requirement (unlevered) | B22: =MAX(0,-MIN(M_CumUnlev)) | C22: 4.8518139e+08 | D22: =IFERROR(B22-C22,"") | E22: =IFERROR(IF(IF(ABS(C22)<10,ABS(B22-C22)<=0.0005,ABS(B22-C22)<=MAX(1,ABS(C22)*0.002)),"✓ matches","changed"),"")
A23: Peak equity | B23: =MAX(0,MAX(M_NetEquity)) | C23: 4.1538324e+08 | D23: =IFERROR(B23-C23,"") | E23: =IFERROR(IF(IF(ABS(C23)<10,ABS(B23-C23)<=0.0005,ABS(B23-C23)<=MAX(1,ABS(C23)*0.002)),"✓ matches","changed"),"")
A24: Equity contributed | B24: =SUM(M_Contrib) | C24: 4.1538324e+08 | D24: =IFERROR(B24-C24,"") | E24: =IFERROR(IF(IF(ABS(C24)<10,ABS(B24-C24)<=0.0005,ABS(B24-C24)<=MAX(1,ABS(C24)*0.002)),"✓ matches","changed"),"")
A25: Senior commitment | B25: =F_SeniorCommit | C25: 3.3985901e+08 | D25: =IFERROR(B25-C25,"") | E25: =IFERROR(IF(IF(ABS(C25)<10,ABS(B25-C25)<=0.0005,ABS(B25-C25)<=MAX(1,ABS(C25)*0.002)),"✓ matches","changed"),"")
A26: Peak senior debt | B26: =MAX(0,MAX(M_Senior))
A27: Loan-to-cost (LTC) | B27: =IF(TotalCost<>0,F_SeniorCommit/TotalCost,0) | C27: 0.45 | D27: =IFERROR(B27-C27,"") | E27: =IFERROR(IF(IF(ABS(C27)<10,ABS(B27-C27)<=0.0005,ABS(B27-C27)<=MAX(1,ABS(C27)*0.002)),"✓ matches","changed"),"")
A28: Funding gap (additional equity) | B28: ='Cash Flow'!B45 | C28: 0 | D28: =IFERROR(B28-C28,"") | E28: =IFERROR(IF(IF(ABS(C28)<10,ABS(B28-C28)<=0.0005,ABS(B28-C28)<=MAX(1,ABS(C28)*0.002)),"✓ matches","changed"),"")
A29: Program & timing
A30: Units | B30: =D_Units | C30: 75 | D30: =IFERROR(B30-C30,"") | E30: =IFERROR(IF(IF(ABS(C30)<10,ABS(B30-C30)<=0.0005,ABS(B30-C30)<=MAX(1,ABS(C30)*0.002)),"✓ matches","changed"),"")
A31: Saleable / leasable area (m²) | B31: =D_Saleable | C31: 8651 | D31: =IFERROR(B31-C31,"") | E31: =IFERROR(IF(IF(ABS(C31)<10,ABS(B31-C31)<=0.0005,ABS(B31-C31)<=MAX(1,ABS(C31)*0.002)),"✓ matches","changed"),"")
A32: Delivery month | B32: =T_Delivery | C32: 32 | D32: =IFERROR(B32-C32,"") | E32: =IFERROR(IF(IF(ABS(C32)<10,ABS(B32-C32)<=0.0005,ABS(B32-C32)<=MAX(1,ABS(C32)*0.002)),"✓ matches","changed"),"")
A33: Project duration (months) | B33: =T_End | C33: 32 | D33: =IFERROR(B33-C33,"") | E33: =IFERROR(IF(IF(ABS(C33)<10,ABS(B33-C33)<=0.0005,ABS(B33-C33)<=MAX(1,ABS(C33)*0.002)),"✓ matches","changed"),"")
A35: Column C is a snapshot of TerraMind's engine when the file was exported. After you edit assumptions in Excel, column B updates and Status shows 'changed'.
A37: Annual summary (Y0 = closing month, Y1 = months 1–12…)
A38: Year | B38: Y0 | C38: Y1 | D38: Y2 | E38: Y3 | F38: Y4 | G38: Y5 | H38: Y6 | I38: Y7 | J38: Y8
A39: Units sold | B39: =SUMPRODUCT(('Cash Flow'!$D$4:$CU$4=0)*M_Sold) | C39: =SUMPRODUCT(('Cash Flow'!$D$4:$CU$4>=1)*('Cash Flow'!$D$4:$CU$4<=12)*M_Sold) | D39: =SUMPRODUCT(('Cash Flow'!$D$4:$CU$4>=13)*('Cash Flow'!$D$4:$CU$4<=24)*M_Sold) | E39: =SUMPRODUCT(('Cash Flow'!$D$4:$CU$4>=25)*('Cash Flow'!$D$4:$CU$4<=36)*M_Sold) | F39: =SUMPRODUCT(('Cash Flow'!$D$4:$CU$4>=37)*('Cash Flow'!$D$4:$CU$4<=48)*M_Sold) | G39: =SUMPRODUCT(('Cash Flow'!$D$4:$CU$4>=49)*('Cash Flow'!$D$4:$CU$4<=60)*M_Sold) | H39: =SUMPRODUCT(('Cash Flow'!$D$4:$CU$4>=61)*('Cash Flow'!$D$4:$CU$4<=72)*M_Sold) | I39: =SUMPRODUCT(('Cash Flow'!$D$4:$CU$4>=73)*('Cash Flow'!$D$4:$CU$4<=84)*M_Sold) | J39: =SUMPRODUCT(('Cash Flow'!$D$4:$CU$4>=85)*('Cash Flow'!$D$4:$CU$4<=96)*M_Sold)
A40: Total outflows | B40: =SUMPRODUCT(('Cash Flow'!$D$4:$CU$4=0)*M_Outflow) | C40: =SUMPRODUCT(('Cash Flow'!$D$4:$CU$4>=1)*('Cash Flow'!$D$4:$CU$4<=12)*M_Outflow) | D40: =SUMPRODUCT(('Cash Flow'!$D$4:$CU$4>=13)*('Cash Flow'!$D$4:$CU$4<=24)*M_Outflow) | E40: =SUMPRODUCT(('Cash Flow'!$D$4:$CU$4>=25)*('Cash Flow'!$D$4:$CU$4<=36)*M_Outflow) | F40: =SUMPRODUCT(('Cash Flow'!$D$4:$CU$4>=37)*('Cash Flow'!$D$4:$CU$4<=48)*M_Outflow) | G40: =SUMPRODUCT(('Cash Flow'!$D$4:$CU$4>=49)*('Cash Flow'!$D$4:$CU$4<=60)*M_Outflow) | H40: =SUMPRODUCT(('Cash Flow'!$D$4:$CU$4>=61)*('Cash Flow'!$D$4:$CU$4<=72)*M_Outflow) | I40: =SUMPRODUCT(('Cash Flow'!$D$4:$CU$4>=73)*('Cash Flow'!$D$4:$CU$4<=84)*M_Outflow) | J40: =SUMPRODUCT(('Cash Flow'!$D$4:$CU$4>=85)*('Cash Flow'!$D$4:$CU$4<=96)*M_Outflow)
A41: Total inflows | B41: =SUMPRODUCT(('Cash Flow'!$D$4:$CU$4=0)*M_Inflow) | C41: =SUMPRODUCT(('Cash Flow'!$D$4:$CU$4>=1)*('Cash Flow'!$D$4:$CU$4<=12)*M_Inflow) | D41: =SUMPRODUCT(('Cash Flow'!$D$4:$CU$4>=13)*('Cash Flow'!$D$4:$CU$4<=24)*M_Inflow) | E41: =SUMPRODUCT(('Cash Flow'!$D$4:$CU$4>=25)*('Cash Flow'!$D$4:$CU$4<=36)*M_Inflow) | F41: =SUMPRODUCT(('Cash Flow'!$D$4:$CU$4>=37)*('Cash Flow'!$D$4:$CU$4<=48)*M_Inflow) | G41: =SUMPRODUCT(('Cash Flow'!$D$4:$CU$4>=49)*('Cash Flow'!$D$4:$CU$4<=60)*M_Inflow) | H41: =SUMPRODUCT(('Cash Flow'!$D$4:$CU$4>=61)*('Cash Flow'!$D$4:$CU$4<=72)*M_Inflow) | I41: =SUMPRODUCT(('Cash Flow'!$D$4:$CU$4>=73)*('Cash Flow'!$D$4:$CU$4<=84)*M_Inflow) | J41: =SUMPRODUCT(('Cash Flow'!$D$4:$CU$4>=85)*('Cash Flow'!$D$4:$CU$4<=96)*M_Inflow)
A42: Unlevered cash flow | B42: =SUMPRODUCT(('Cash Flow'!$D$4:$CU$4=0)*M_Unlev) | C42: =SUMPRODUCT(('Cash Flow'!$D$4:$CU$4>=1)*('Cash Flow'!$D$4:$CU$4<=12)*M_Unlev) | D42: =SUMPRODUCT(('Cash Flow'!$D$4:$CU$4>=13)*('Cash Flow'!$D$4:$CU$4<=24)*M_Unlev) | E42: =SUMPRODUCT(('Cash Flow'!$D$4:$CU$4>=25)*('Cash Flow'!$D$4:$CU$4<=36)*M_Unlev) | F42: =SUMPRODUCT(('Cash Flow'!$D$4:$CU$4>=37)*('Cash Flow'!$D$4:$CU$4<=48)*M_Unlev) | G42: =SUMPRODUCT(('Cash Flow'!$D$4:$CU$4>=49)*('Cash Flow'!$D$4:$CU$4<=60)*M_Unlev) | H42: =SUMPRODUCT(('Cash Flow'!$D$4:$CU$4>=61)*('Cash Flow'!$D$4:$CU$4<=72)*M_Unlev) | I42: =SUMPRODUCT(('Cash Flow'!$D$4:$CU$4>=73)*('Cash Flow'!$D$4:$CU$4<=84)*M_Unlev) | J42: =SUMPRODUCT(('Cash Flow'!$D$4:$CU$4>=85)*('Cash Flow'!$D$4:$CU$4<=96)*M_Unlev)
A43: Equity contributions | B43: =SUMPRODUCT(('Cash Flow'!$D$4:$CU$4=0)*M_Contrib) | C43: =SUMPRODUCT(('Cash Flow'!$D$4:$CU$4>=1)*('Cash Flow'!$D$4:$CU$4<=12)*M_Contrib) | D43: =SUMPRODUCT(('Cash Flow'!$D$4:$CU$4>=13)*('Cash Flow'!$D$4:$CU$4<=24)*M_Contrib) | E43: =SUMPRODUCT(('Cash Flow'!$D$4:$CU$4>=25)*('Cash Flow'!$D$4:$CU$4<=36)*M_Contrib) | F43: =SUMPRODUCT(('Cash Flow'!$D$4:$CU$4>=37)*('Cash Flow'!$D$4:$CU$4<=48)*M_Contrib) | G43: =SUMPRODUCT(('Cash Flow'!$D$4:$CU$4>=49)*('Cash Flow'!$D$4:$CU$4<=60)*M_Contrib) | H43: =SUMPRODUCT(('Cash Flow'!$D$4:$CU$4>=61)*('Cash Flow'!$D$4:$CU$4<=72)*M_Contrib) | I43: =SUMPRODUCT(('Cash Flow'!$D$4:$CU$4>=73)*('Cash Flow'!$D$4:$CU$4<=84)*M_Contrib) | J43: =SUMPRODUCT(('Cash Flow'!$D$4:$CU$4>=85)*('Cash Flow'!$D$4:$CU$4<=96)*M_Contrib)
A44: Equity distributions | B44: =SUMPRODUCT(('Cash Flow'!$D$4:$CU$4=0)*M_Dist) | C44: =SUMPRODUCT(('Cash Flow'!$D$4:$CU$4>=1)*('Cash Flow'!$D$4:$CU$4<=12)*M_Dist) | D44: =SUMPRODUCT(('Cash Flow'!$D$4:$CU$4>=13)*('Cash Flow'!$D$4:$CU$4<=24)*M_Dist) | E44: =SUMPRODUCT(('Cash Flow'!$D$4:$CU$4>=25)*('Cash Flow'!$D$4:$CU$4<=36)*M_Dist) | F44: =SUMPRODUCT(('Cash Flow'!$D$4:$CU$4>=37)*('Cash Flow'!$D$4:$CU$4<=48)*M_Dist) | G44: =SUMPRODUCT(('Cash Flow'!$D$4:$CU$4>=49)*('Cash Flow'!$D$4:$CU$4<=60)*M_Dist) | H44: =SUMPRODUCT(('Cash Flow'!$D$4:$CU$4>=61)*('Cash Flow'!$D$4:$CU$4<=72)*M_Dist) | I44: =SUMPRODUCT(('Cash Flow'!$D$4:$CU$4>=73)*('Cash Flow'!$D$4:$CU$4<=84)*M_Dist) | J44: =SUMPRODUCT(('Cash Flow'!$D$4:$CU$4>=85)*('Cash Flow'!$D$4:$CU$4<=96)*M_Dist)
A45: Levered cash flow | B45: =SUMPRODUCT(('Cash Flow'!$D$4:$CU$4=0)*M_Lev) | C45: =SUMPRODUCT(('Cash Flow'!$D$4:$CU$4>=1)*('Cash Flow'!$D$4:$CU$4<=12)*M_Lev) | D45: =SUMPRODUCT(('Cash Flow'!$D$4:$CU$4>=13)*('Cash Flow'!$D$4:$CU$4<=24)*M_Lev) | E45: =SUMPRODUCT(('Cash Flow'!$D$4:$CU$4>=25)*('Cash Flow'!$D$4:$CU$4<=36)*M_Lev) | F45: =SUMPRODUCT(('Cash Flow'!$D$4:$CU$4>=37)*('Cash Flow'!$D$4:$CU$4<=48)*M_Lev) | G45: =SUMPRODUCT(('Cash Flow'!$D$4:$CU$4>=49)*('Cash Flow'!$D$4:$CU$4<=60)*M_Lev) | H45: =SUMPRODUCT(('Cash Flow'!$D$4:$CU$4>=61)*('Cash Flow'!$D$4:$CU$4<=72)*M_Lev) | I45: =SUMPRODUCT(('Cash Flow'!$D$4:$CU$4>=73)*('Cash Flow'!$D$4:$CU$4<=84)*M_Lev) | J45: =SUMPRODUCT(('Cash Flow'!$D$4:$CU$4>=85)*('Cash Flow'!$D$4:$CU$4<=96)*M_Lev)
A47: Cost by category
A48: Land & acquisition | B48: =SUM(M_land)+SUM(M_acq) | C48: =IF(TotalCost<>0,B48/TotalCost,0)
A49: Hard costs | B49: =SUM(M_hard) | C49: =IF(TotalCost<>0,B49/TotalCost,0)
A50: Soft costs | B50: =SUM(M_soft) | C50: =IF(TotalCost<>0,B50/TotalCost,0)
A51: Contingency & developer fee | B51: =SUM(M_cont)+SUM(M_fee) | C51: =IF(TotalCost<>0,B51/TotalCost,0)
A52: Sales & marketing | B52: =IF(in_mode_sale=1,SUM(M_SalesCost),0) | C52: =IF(TotalCost<>0,B52/TotalCost,0)
A53: User-defined & custom costs | B53: =SUM(M_cv)+SUM(M_cflow) | C53: =IF(TotalCost<>0,B53/TotalCost,0)
A54: Financing | B54: =FinCost | C54: =IF(TotalCost<>0,B54/TotalCost,0)

Sheet Assumptions
A1: Assumptions
A2: All inputs of the model. Blue cells are inputs: change any of them and the whole workbook recalculates.
A4: Assumption | B4: Value | C4: Unit | D4: Source / note
A5: Project
A6: Project | B6: Polanco Residences (fictional)
A7: Currency | B7: MXN
A8: For-sale model (1) or rental model (0) | B8: 1 | D8: Switches the revenue logic; set by the project's business model
A9: Ground-up development (1) or acquisition (0) | B9: 1 | D9: Switches the revenue logic; set by the project's business model
A10: Circuit breaker: size debt on cost incl. financing (1 = on, 0 = break the circular loop) | B10: 1 | D10: Switches the revenue logic; set by the project's business model
A11: Site & acquisition
A12: Land area | B12: 1800 | C12: m² | D12: Source: demo
A13: Land / property acquisition price | B13: 265000000 | C13: MXN | D13: Source: demo
A14: Transfer tax (ISAI) | B14: 0.045 | C14: % | D14: Source: demo
A15: Notary & legal fees | B15: 0.015 | C15: % | D15: Source: demo
A16: Brokerage on acquisition | B16: 0.01 | C16: % | D16: Source: demo
A17: Due diligence & closing (fixed) | B17: 1500000 | C17: MXN | D17: Source: demo
A18: Regulation & zoning (legal limits)
A19: Maximum stories above ground | B19: 8 | C19: stories | D19: Source: demo
A20: Minimum open (unbuilt) area | B20: 0.25 | C20: % | D20: Source: demo
A21: Maximum FAR (CUS) | C21: x land | D21: Not set
A22: Maximum height | C22: m | D22: Not set
A23: Density: land area per dwelling | C23: m²/unit | D23: Not set
A24: Maximum dwellings | C24: units | D24: Not set
A25: Maximum underground levels | B25: 4 | C25: levels | D25: Source: demo
A26: Minimum parking per unit | C26: spaces/unit | D26: Not set
A27: Maximum parking per unit | B27: 3 | C27: spaces/unit | D27: Source: demo
A28: Development configuration
A29: Number of buildings | B29: 1 | C29: count | D29: Source: demo
A30: Stories above ground | B30: 8 | C30: stories | D30: Source: demo
A31: Underground levels | B31: 3 | C31: levels | D31: Source: demo
A32: Building footprint | C32: m² | D32: Not set
A33: Saleable / gross efficiency | B33: 0.82 | C33: % | D33: Source: demo
A34: Parking spaces | B34: 112 | C34: spaces | D34: Source: demo
A35: Gross area per parking space | B35: 28 | C35: m²/space | D35: Source: demo
A36: Amenity area (inside GBA) | B36: 250 | C36: m² | D36: Source: demo
A37: Construction quality | B37: high | D37: Source: demo
A38: Existing rentable area (acquisitions) | C38: m² | D38: Not set
A39: Sales revenue
A40: Base sale price | B40: 108000 | C40: MXN/m² | D40: Source: demo
A41: Average floor / view premium | B41: 0.03 | C41: % | D41: Source: demo
A42: Terrace value vs interior m² | B42: 0.4 | C42: % | D42: Source: demo
A43: Average discount | B43: 0.02 | C43: % | D43: Source: demo
A44: Annual price escalation | B44: 0.05 | C44: % | D44: Source: demo
A45: Sales absorption (gross) | B45: 3 | C45: units/month | D45: Source: demo
A46: Cancellations | B46: 0.05 | C46: % | D46: Source: demo
A47: Presales start vs construction start | B47: -3 | C47: months | D47: Source: demo
A48: Deposit at contract | B48: 0.1 | C48: % | D48: Source: demo
A49: Installments during construction | B49: 0.2 | C49: % | D49: Source: demo
A50: Balance at delivery / closing | B50: 0.7 | C50: % | D50: Source: demo
A51: Sales commissions | B51: 0.03 | C51: % | D51: Source: demo
A52: Marketing & sales office | B52: 0.02 | C52: % of revenue | D52: Source: demo
A53: Rental income
A54: Market rent | C54: MXN/m²/month | D54: Not set
A55: Stabilized vacancy | B55: 0.05 | C55: % | D55: Source: default (unverified)
A56: Rent concessions | B56: 0.01 | C56: % | D56: Source: default (unverified)
A57: Operating expenses | B57: 0.3 | C57: % of EGI | D57: Source: default (unverified)
A58: Annual rent growth | B58: 0.04 | C58: % | D58: Source: default (unverified)
A59: Lease-up period | B59: 12 | C59: months | D59: Source: default (unverified)
A60: Exit cap rate | C60: % | D60: Not set
A61: Exit selling costs | B61: 0.02 | C61: % | D61: Source: default (unverified)
A62: Hold period after delivery | B62: 5 | C62: years | D62: Source: default (unverified)
A63: Development budget
A64: Hard cost above ground | B64: 24000 | C64: MXN/m² GBA | D64: Source: demo
A65: Hard cost below ground (parking) | B65: 14000 | C65: MXN/m² | D65: Source: demo
A66: Demolition & site preparation (fixed) | B66: 2500000 | C66: MXN | D66: Source: demo
A67: Infrastructure / impact fees (fixed) | B67: 6000000 | C67: MXN | D67: Source: demo
A68: Renovation / CAPEX budget (acquisitions) | C68: MXN | D68: Not set
A69: Architecture & engineering | B69: 0.05 | C69: % of hard | D69: Source: demo
A70: Permits & licenses | B70: 0.025 | C70: % of hard | D70: Source: demo
A71: Project management & supervision | B71: 0.035 | C71: % of hard | D71: Source: demo
A72: Insurance, consultants & other soft | B72: 0.015 | C72: % of hard | D72: Source: demo
A73: Contingency | B73: 0.05 | C73: % of hard + soft | D73: Source: demo
A74: Construction spending curve | B74: s_curve | D74: Source: default (unverified)
A75: Annual construction cost escalation | B75: 0.05 | C75: % | D75: Source: demo
A76: Developer fee | B76: 0.03 | C76: % of hard + soft | D76: Source: demo
A77: Schedule
A78: Design & permits (pre-development) | B78: 8 | C78: months | D78: Source: demo
A79: Construction duration | B79: 24 | C79: months | D79: Source: demo
A80: Financing
A81: Senior debt (loan-to-cost) | B81: 0.45 | C81: % | D81: Source: demo
A82: Senior rate type | B82: floating | D82: Source: demo
A83: Reference rate (e.g. TIIE 28d) | B83: 0.0725 | C83: % | D83: Source: demo
A84: Senior spread over reference | B84: 0.035 | C84: % | D84: Source: demo
A85: Senior fixed rate | C85: % | D85: Not set
A86: Origination fee | B86: 0.01 | C86: % of commitment | D86: Source: demo
A87: Commitment fee on undrawn | B87: 0.005 | C87: % p.a. | D87: Source: demo
A88: Capitalize interest during construction | B88: TRUE | D88: Source: demo
A89: Senior loan maturity (from first draw) | B89: 42 | C89: months | D89: Source: demo
A90: Cash sweep to debt after delivery | B90: 1 | C90: % | D90: Source: demo
A91: Amortization (term loans, rentals) | B91: 25 | C91: years | D91: Source: default (unverified)
A92: Mezzanine (loan-to-cost) | B92: 0 | C92: % | D92: Source: demo
A93: Mezzanine rate | C93: % | D93: Not set
A94: Sponsor share of equity | B94: 0.2 | C94: % | D94: Source: demo
A95: Investor preferred return | B95: 0.1 | C95: % p.a. | D95: Source: demo
A96: Sponsor promote above pref | B96: 0.2 | C96: % | D96: Source: demo
A97: Covenant: max LTC | B97: 0.6 | C97: % | D97: Source: demo
A98: Covenant: max LTV (on GDV) | B98: 0.45 | C98: % | D98: Source: demo
A99: Covenant: presales before first draw | B99: 0.3 | C99: % of units | D99: Source: demo
A100: Covenant: minimum DSCR | B100: 1.25 | C100: x | D100: Source: demo
A101: Valuation
...

Sheet Development
A1: Development program
A2: Areas, units and legal capacity calculated from the assumptions
A4: Land area (m²) | B4: =in_site_land_area
A5: Maximum site coverage (m²) | B5: =D_Land*(1-in_reg_min_open_area_pct)
A6: Maximum FAR | B6: =IF(in_reg_max_far="",in_reg_max_stories*(1-in_reg_min_open_area_pct),in_reg_max_far)
A7: Maximum buildable GBA (capacity, m²) | B7: =D_Land*D_MaxFAR
A8: Building footprint (m²) | B8: =IF(in_dev_footprint="",D_MaxCov,in_dev_footprint)
A9: Above-ground GBA (m²) | B9: =IF(in_ground_up=1,D_Footprint*in_dev_stories,IF(in_dev_efficiency_pct>0,in_dev_existing_rentable_area/in_dev_efficiency_pct,0))
A10: Saleable / leasable area (m²) | B10: =IF(in_ground_up=1,MAX(D_GBA-in_dev_amenity_area,0)*in_dev_efficiency_pct,in_dev_existing_rentable_area)
A12: Units by type
A13: Type | B13: Units | C13: Area (m²) | D13: Unit price today | E13: Price per m²
A14: =IF(Assumptions!A112="","",Assumptions!A112) | B14: =IF(Assumptions!B112>0,INT(D_Saleable*Assumptions!C112/Assumptions!B112+1E-9),0) | C14: =B14*Assumptions!B112 | D14: =Assumptions!B112*P_Eff*(1+Assumptions!E112)*(1+in_rev_floor_view_premium_pct)+Assumptions!D112*P_Eff*in_rev_terrace_value_pct | E14: =IF(Assumptions!B112>0,D14/Assumptions!B112,0)
A15: =IF(Assumptions!A113="","",Assumptions!A113) | B15: =IF(Assumptions!B113>0,INT(D_Saleable*Assumptions!C113/Assumptions!B113+1E-9),0) | C15: =B15*Assumptions!B113 | D15: =Assumptions!B113*P_Eff*(1+Assumptions!E113)*(1+in_rev_floor_view_premium_pct)+Assumptions!D113*P_Eff*in_rev_terrace_value_pct | E15: =IF(Assumptions!B113>0,D15/Assumptions!B113,0)
A16: =IF(Assumptions!A114="","",Assumptions!A114) | B16: =IF(Assumptions!B114>0,INT(D_Saleable*Assumptions!C114/Assumptions!B114+1E-9),0) | C16: =B16*Assumptions!B114 | D16: =Assumptions!B114*P_Eff*(1+Assumptions!E114)*(1+in_rev_floor_view_premium_pct)+Assumptions!D114*P_Eff*in_rev_terrace_value_pct | E16: =IF(Assumptions!B114>0,D16/Assumptions!B114,0)
A17: =IF(Assumptions!A115="","",Assumptions!A115) | B17: =IF(Assumptions!B115>0,INT(D_Saleable*Assumptions!C115/Assumptions!B115+1E-9),0) | C17: =B17*Assumptions!B115 | D17: =Assumptions!B115*P_Eff*(1+Assumptions!E115)*(1+in_rev_floor_view_premium_pct)+Assumptions!D115*P_Eff*in_rev_terrace_value_pct | E17: =IF(Assumptions!B115>0,D17/Assumptions!B115,0)
A18: =IF(Assumptions!A116="","",Assumptions!A116) | B18: =IF(Assumptions!B116>0,INT(D_Saleable*Assumptions!C116/Assumptions!B116+1E-9),0) | C18: =B18*Assumptions!B116 | D18: =Assumptions!B116*P_Eff*(1+Assumptions!E116)*(1+in_rev_floor_view_premium_pct)+Assumptions!D116*P_Eff*in_rev_terrace_value_pct | E18: =IF(Assumptions!B116>0,D18/Assumptions!B116,0)
A19: =IF(Assumptions!A117="","",Assumptions!A117) | B19: =IF(Assumptions!B117>0,INT(D_Saleable*Assumptions!C117/Assumptions!B117+1E-9),0) | C19: =B19*Assumptions!B117 | D19: =Assumptions!B117*P_Eff*(1+Assumptions!E117)*(1+in_rev_floor_view_premium_pct)+Assumptions!D117*P_Eff*in_rev_terrace_value_pct | E19: =IF(Assumptions!B117>0,D19/Assumptions!B117,0)
A20: =IF(Assumptions!A118="","",Assumptions!A118) | B20: =IF(Assumptions!B118>0,INT(D_Saleable*Assumptions!C118/Assumptions!B118+1E-9),0) | C20: =B20*Assumptions!B118 | D20: =Assumptions!B118*P_Eff*(1+Assumptions!E118)*(1+in_rev_floor_view_premium_pct)+Assumptions!D118*P_Eff*in_rev_terrace_value_pct | E20: =IF(Assumptions!B118>0,D20/Assumptions!B118,0)
A21: =IF(Assumptions!A119="","",Assumptions!A119) | B21: =IF(Assumptions!B119>0,INT(D_Saleable*Assumptions!C119/Assumptions!B119+1E-9),0) | C21: =B21*Assumptions!B119 | D21: =Assumptions!B119*P_Eff*(1+Assumptions!E119)*(1+in_rev_floor_view_premium_pct)+Assumptions!D119*P_Eff*in_rev_terrace_value_pct | E21: =IF(Assumptions!B119>0,D21/Assumptions!B119,0)
A22: Total | B22: =SUM(B14:B21) | C22: =SUM(C14:C21)
A24: Effective base price per m² (incl. green premium and user price variables) | B24: =IF(in_mode_sale=1,in_rev_price_per_area,0)*(1+in_green_sale_prem)*CV_PriceMult
A25: Price multiplier from user-defined variables | B25: =EXP(SUMPRODUCT((cv_effect="price_pct")*LN(1+cv_value)))
A26: Average unit price today | B26: =IF(D_Units>0,SUMPRODUCT(D_UnitsRange,D_PriceRange)/D_Units,0)
A27: Terrace area (m²) | B27: =SUMPRODUCT(B14:B21,Assumptions!D112:D119)
A28: Parking spaces | B28: =IF(in_dev_parking_spaces="",IF(in_reg_parking_min_per_unit="",0,ROUNDUP(in_reg_parking_min_per_unit*D_Units,0)),in_dev_parking_spaces)
A29: Below-grade area (m²) | B29: =IF(in_ground_up=1,D_Parking*in_dev_parking_area_per_space,0)
A30: Underground levels needed | B30: =IF(AND(D_Land>0,D_Below>0),ROUNDUP(D_Below/(D_Land*0.95),0),0)
A31: Density limit (max dwellings) | B31: =IF(in_reg_min_land_per_unit="","No limit entered",INT(D_Land/in_reg_min_land_per_unit))
A33: Compliance checks (TRUE = within the legal limit)
A34: Stories ≤ maximum stories | B34: =IF(in_reg_max_stories="",TRUE,in_dev_stories<=in_reg_max_stories)
A35: GBA ≤ FAR capacity | B35: =D_GBA<=D_Capacity*1.0001
A36: Units ≤ density limit | B36: =IF(ISNUMBER(D_MaxUnits),D_Units<=D_MaxUnits,TRUE)
A37: Underground levels ≤ maximum | B37: =IF(in_reg_max_underground_levels="",TRUE,in_dev_levels_below<=in_reg_max_underground_levels)

Sheet Construction
A1: Construction & development cost schedule
A2: Monthly, MXN. Month 0 = land closing; construction follows pre-development.
A4: Month | B4: Total | C4: Unit / note | D4: 0 | E4: =D4+1 | F4: =E4+1 | G4: =F4+1 | H4: =G4+1 | I4: =H4+1 | J4: =I4+1 | K4: =J4+1 | L4: =K4+1 | ... CU4: =CT4+1
A5: Pre-development months | B5: =IF(in_ground_up=1,IF(in_sch_predev_months="",0,in_sch_predev_months),IF(in_sch_predev_months="",0,in_sch_predev_months))
A6: Construction months | B6: =IF(in_sch_construction_months="",0,in_sch_construction_months)
A7: Construction start month | B7: =T_Predev
A8: Delivery month | B8: =T_Predev+T_Con
A9: Above-ground hard cost (today's prices) | B9: =IF(in_ground_up=1,D_GBA*in_cost_hard_per_area,IF(in_cost_renovation_budget="",0,in_cost_renovation_budget))
A10: Below-grade hard cost | B10: =IF(in_ground_up=1,D_Below*IF(in_cost_below_grade_per_area="",0,in_cost_below_grade_per_area),0)
A11: Fixed site costs (demolition + infrastructure) | B11: =N(in_cost_demolition)+N(in_cost_infrastructure_fees)
A12: Hard-cost base for % fees | B12: =C_HardAbove+C_HardBelow+C_FixedSite+in_green_capex
A13: Soft costs (design + permits + PM + other) | B13: =C_HardBase*(in_cost_design_pct+in_cost_permits_pct+in_cost_pm_supervision_pct+in_cost_insurance_other_pct)
A14: Contingency | B14: =(C_HardBase+C_Soft)*in_cost_contingency_pct
A15: Developer fee | B15: =(C_HardBase+C_Soft)*in_cost_developer_fee_pct
A16: User-defined costs spread over construction | B16: =SUMPRODUCT((cv_effect="cost_fixed")*(cv_timing="construction")*cv_value)+SUMPRODUCT((cv_effect="cost_per_area")*cv_value)*D_GBA+SUMPRODUCT((cv_effect="cost_per_unit")*cv_value)*D_Units+SUMPRODUCT((cv_effect="cost_pct_hard")*cv_value)*C_HardBase
A19: Pre-development month (flag) | D19: =IF(AND(D$4>=1,D$4<=T_Predev),1,0) | E19: =IF(AND(E$4>=1,E$4<=T_Predev),1,0) | F19: =IF(AND(F$4>=1,F$4<=T_Predev),1,0) | G19: =IF(AND(G$4>=1,G$4<=T_Predev),1,0) | H19: =IF(AND(H$4>=1,H$4<=T_Predev),1,0) | I19: =IF(AND(I$4>=1,I$4<=T_Predev),1,0) | J19: =IF(AND(J$4>=1,J$4<=T_Predev),1,0) | K19: =IF(AND(K$4>=1,K$4<=T_Predev),1,0) | ... CU19: =IF(AND(CU$4>=1,CU$4<=T_Predev),1,0)
A20: Construction month (flag) | D20: =IF(AND(D$4>T_ConStart,D$4<=T_Delivery),1,0) | E20: =IF(AND(E$4>T_ConStart,E$4<=T_Delivery),1,0) | F20: =IF(AND(F$4>T_ConStart,F$4<=T_Delivery),1,0) | G20: =IF(AND(G$4>T_ConStart,G$4<=T_Delivery),1,0) | H20: =IF(AND(H$4>T_ConStart,H$4<=T_Delivery),1,0) | I20: =IF(AND(I$4>T_ConStart,I$4<=T_Delivery),1,0) | J20: =IF(AND(J$4>T_ConStart,J$4<=T_Delivery),1,0) | K20: =IF(AND(K$4>T_ConStart,K$4<=T_Delivery),1,0) | ... CU20: =IF(AND(CU$4>T_ConStart,CU$4<=T_Delivery),1,0)
A21: Construction spending weight (curve) | B21: =SUM(D21:CU21) | C21: S-curve unless changed in Assumptions | D21: =IF(D20=1,IF(in_cost_curve="linear",1/T_Con,IF(in_cost_curve="front_loaded",(T_Con-(D$4-T_ConStart)+1)/(T_Con*(T_Con+1)/2),IF(in_cost_curve="back_loaded",(D$4-T_ConStart)/(T_Con*(T_Con+1)/2),(COS(PI()*(D$4-T_ConStart-1)/T_Con)-COS(PI()*(D$4-T_ConStart)/T_Con))/2))),0) | E21: =IF(E20=1,IF(in_cost_curve="linear",1/T_Con,IF(in_cost_curve="front_loaded",(T_Con-(E$4-T_ConStart)+1)/(T_Con*(T_Con+1)/2),IF(in_cost_curve="back_loaded",(E$4-T_ConStart)/(T_Con*(T_Con+1)/2),(COS(PI()*(E$4-T_ConStart-1)/T_Con)-COS(PI()*(E$4-T_ConStart)/T_Con))/2))),0) | F21: =IF(F20=1,IF(in_cost_curve="linear",1/T_Con,IF(in_cost_curve="front_loaded",(T_Con-(F$4-T_ConStart)+1)/(T_Con*(T_Con+1)/2),IF(in_cost_curve="back_loaded",(F$4-T_ConStart)/(T_Con*(T_Con+1)/2),(COS(PI()*(F$4-T_ConStart-1)/T_Con)-COS(PI()*(F$4-T_ConStart)/T_Con))/2))),0) | G21: =IF(G20=1,IF(in_cost_curve="linear",1/T_Con,IF(in_cost_curve="front_loaded",(T_Con-(G$4-T_ConStart)+1)/(T_Con*(T_Con+1)/2),IF(in_cost_curve="back_loaded",(G$4-T_ConStart)/(T_Con*(T_Con+1)/2),(COS(PI()*(G$4-T_ConStart-1)/T_Con)-COS(PI()*(G$4-T_ConStart)/T_Con))/2))),0) | H21: =IF(H20=1,IF(in_cost_curve="linear",1/T_Con,IF(in_cost_curve="front_loaded",(T_Con-(H$4-T_ConStart)+1)/(T_Con*(T_Con+1)/2),IF(in_cost_curve="back_loaded",(H$4-T_ConStart)/(T_Con*(T_Con+1)/2),(COS(PI()*(H$4-T_ConStart-1)/T_Con)-COS(PI()*(H$4-T_ConStart)/T_Con))/2))),0) | I21: =IF(I20=1,IF(in_cost_curve="linear",1/T_Con,IF(in_cost_curve="front_loaded",(T_Con-(I$4-T_ConStart)+1)/(T_Con*(T_Con+1)/2),IF(in_cost_curve="back_loaded",(I$4-T_ConStart)/(T_Con*(T_Con+1)/2),(COS(PI()*(I$4-T_ConStart-1)/T_Con)-COS(PI()*(I$4-T_ConStart)/T_Con))/2))),0) | J21: =IF(J20=1,IF(in_cost_curve="linear",1/T_Con,IF(in_cost_curve="front_loaded",(T_Con-(J$4-T_ConStart)+1)/(T_Con*(T_Con+1)/2),IF(in_cost_curve="back_loaded",(J$4-T_ConStart)/(T_Con*(T_Con+1)/2),(COS(PI()*(J$4-T_ConStart-1)/T_Con)-COS(PI()*(J$4-T_ConStart)/T_Con))/2))),0) | K21: =IF(K20=1,IF(in_cost_curve="linear",1/T_Con,IF(in_cost_curve="front_loaded",(T_Con-(K$4-T_ConStart)+1)/(T_Con*(T_Con+1)/2),IF(in_cost_curve="back_loaded",(K$4-T_ConStart)/(T_Con*(T_Con+1)/2),(COS(PI()*(K$4-T_ConStart-1)/T_Con)-COS(PI()*(K$4-T_ConStart)/T_Con))/2))),0) | ... CU21: =IF(CU20=1,IF(in_cost_curve="linear",1/T_Con,IF(in_cost_curve="front_loaded",(T_Con-(CU$4-T_ConStart)+1)/(T_Con*(T_Con+1)/2),IF(in_cost_curve="back_loaded",(CU$4-T_ConStart)/(T_Con*(T_Con+1)/2),(COS(PI()*(CU$4-T_ConStart-1)/T_Con)-COS(PI()*(CU$4-T_ConStart)/T_Con))/2))),0)
A22: Construction cost escalation factor | D22: =(1+in_cost_escalation_pct)^(D$4/12) | E22: =(1+in_cost_escalation_pct)^(E$4/12) | F22: =(1+in_cost_escalation_pct)^(F$4/12) | G22: =(1+in_cost_escalation_pct)^(G$4/12) | H22: =(1+in_cost_escalation_pct)^(H$4/12) | I22: =(1+in_cost_escalation_pct)^(I$4/12) | J22: =(1+in_cost_escalation_pct)^(J$4/12) | K22: =(1+in_cost_escalation_pct)^(K$4/12) | ... CU22: =(1+in_cost_escalation_pct)^(CU$4/12)
A23: Costs
A24: Land / property price | B24: =SUM(D24:CU24) | D24: =IF(SUM(lp_pct)=0,IF(D$4=0,in_site_land_price,0),SUMPRODUCT((lp_month=D$4)*lp_pct)*in_site_land_price) | E24: =IF(SUM(lp_pct)=0,IF(E$4=0,in_site_land_price,0),SUMPRODUCT((lp_month=E$4)*lp_pct)*in_site_land_price) | F24: =IF(SUM(lp_pct)=0,IF(F$4=0,in_site_land_price,0),SUMPRODUCT((lp_month=F$4)*lp_pct)*in_site_land_price) | G24: =IF(SUM(lp_pct)=0,IF(G$4=0,in_site_land_price,0),SUMPRODUCT((lp_month=G$4)*lp_pct)*in_site_land_price) | H24: =IF(SUM(lp_pct)=0,IF(H$4=0,in_site_land_price,0),SUMPRODUCT((lp_month=H$4)*lp_pct)*in_site_land_price) | I24: =IF(SUM(lp_pct)=0,IF(I$4=0,in_site_land_price,0),SUMPRODUCT((lp_month=I$4)*lp_pct)*in_site_land_price) | J24: =IF(SUM(lp_pct)=0,IF(J$4=0,in_site_land_price,0),SUMPRODUCT((lp_month=J$4)*lp_pct)*in_site_land_price) | K24: =IF(SUM(lp_pct)=0,IF(K$4=0,in_site_land_price,0),SUMPRODUCT((lp_month=K$4)*lp_pct)*in_site_land_price) | ... CU24: =IF(SUM(lp_pct)=0,IF(CU$4=0,in_site_land_price,0),SUMPRODUCT((lp_month=CU$4)*lp_pct)*in_site_land_price)
A25: Acquisition taxes, notary, brokerage & due diligence | B25: =SUM(D25:CU25) | D25: =IF(D$4=0,in_site_land_price*(in_site_transfer_tax_pct+in_site_legal_notary_pct+in_site_brokerage_pct)+N(in_site_due_diligence),0) | E25: =IF(E$4=0,in_site_land_price*(in_site_transfer_tax_pct+in_site_legal_notary_pct+in_site_brokerage_pct)+N(in_site_due_diligence),0) | F25: =IF(F$4=0,in_site_land_price*(in_site_transfer_tax_pct+in_site_legal_notary_pct+in_site_brokerage_pct)+N(in_site_due_diligence),0) | G25: =IF(G$4=0,in_site_land_price*(in_site_transfer_tax_pct+in_site_legal_notary_pct+in_site_brokerage_pct)+N(in_site_due_diligence),0) | H25: =IF(H$4=0,in_site_land_price*(in_site_transfer_tax_pct+in_site_legal_notary_pct+in_site_brokerage_pct)+N(in_site_due_diligence),0) | I25: =IF(I$4=0,in_site_land_price*(in_site_transfer_tax_pct+in_site_legal_notary_pct+in_site_brokerage_pct)+N(in_site_due_diligence),0) | J25: =IF(J$4=0,in_site_land_price*(in_site_transfer_tax_pct+in_site_legal_notary_pct+in_site_brokerage_pct)+N(in_site_due_diligence),0) | K25: =IF(K$4=0,in_site_land_price*(in_site_transfer_tax_pct+in_site_legal_notary_pct+in_site_brokerage_pct)+N(in_site_due_diligence),0) | ... CU25: =IF(CU$4=0,in_site_land_price*(in_site_transfer_tax_pct+in_site_legal_notary_pct+in_site_brokerage_pct)+N(in_site_due_diligence),0)
A26: Hard costs (escalated) incl. sustainability capex | B26: =SUM(D26:CU26) | D26: =(C_HardAbove+C_HardBelow+in_green_capex)*D21*D22+IF(D$4=IF(T_Con>0,T_ConStart+1,T_ConStart),C_FixedSite,0) | E26: =(C_HardAbove+C_HardBelow+in_green_capex)*E21*E22+IF(E$4=IF(T_Con>0,T_ConStart+1,T_ConStart),C_FixedSite,0) | F26: =(C_HardAbove+C_HardBelow+in_green_capex)*F21*F22+IF(F$4=IF(T_Con>0,T_ConStart+1,T_ConStart),C_FixedSite,0) | G26: =(C_HardAbove+C_HardBelow+in_green_capex)*G21*G22+IF(G$4=IF(T_Con>0,T_ConStart+1,T_ConStart),C_FixedSite,0) | H26: =(C_HardAbove+C_HardBelow+in_green_capex)*H21*H22+IF(H$4=IF(T_Con>0,T_ConStart+1,T_ConStart),C_FixedSite,0) | I26: =(C_HardAbove+C_HardBelow+in_green_capex)*I21*I22+IF(I$4=IF(T_Con>0,T_ConStart+1,T_ConStart),C_FixedSite,0) | J26: =(C_HardAbove+C_HardBelow+in_green_capex)*J21*J22+IF(J$4=IF(T_Con>0,T_ConStart+1,T_ConStart),C_FixedSite,0) | K26: =(C_HardAbove+C_HardBelow+in_green_capex)*K21*K22+IF(K$4=IF(T_Con>0,T_ConStart+1,T_ConStart),C_FixedSite,0) | ... CU26: =(C_HardAbove+C_HardBelow+in_green_capex)*CU21*CU22+IF(CU$4=IF(T_Con>0,T_ConStart+1,T_ConStart),C_FixedSite,0)
A27: Soft costs | B27: =SUM(D27:CU27) | D27: =IF(T_Predev>0,C_HardBase*in_cost_design_pct*0.6*D19/T_Predev+C_HardBase*in_cost_design_pct*0.4*D20/MAX(T_Con,1),C_HardBase*in_cost_design_pct*D20/MAX(T_Con,1))+IF(D$4=T_ConStart,C_HardBase*in_cost_permits_pct,0)+C_HardBase*(in_cost_pm_supervision_pct+in_cost_insurance_other_pct)*D20/MAX(T_Con,1) | E27: =IF(T_Predev>0,C_HardBase*in_cost_design_pct*0.6*E19/T_Predev+C_HardBase*in_cost_design_pct*0.4*E20/MAX(T_Con,1),C_HardBase*in_cost_design_pct*E20/MAX(T_Con,1))+IF(E$4=T_ConStart,C_HardBase*in_cost_permits_pct,0)+C_HardBase*(in_cost_pm_supervision_pct+in_cost_insurance_other_pct)*E20/MAX(T_Con,1) | F27: =IF(T_Predev>0,C_HardBase*in_cost_design_pct*0.6*F19/T_Predev+C_HardBase*in_cost_design_pct*0.4*F20/MAX(T_Con,1),C_HardBase*in_cost_design_pct*F20/MAX(T_Con,1))+IF(F$4=T_ConStart,C_HardBase*in_cost_permits_pct,0)+C_HardBase*(in_cost_pm_supervision_pct+in_cost_insurance_other_pct)*F20/MAX(T_Con,1) | G27: =IF(T_Predev>0,C_HardBase*in_cost_design_pct*0.6*G19/T_Predev+C_HardBase*in_cost_design_pct*0.4*G20/MAX(T_Con,1),C_HardBase*in_cost_design_pct*G20/MAX(T_Con,1))+IF(G$4=T_ConStart,C_HardBase*in_cost_permits_pct,0)+C_HardBase*(in_cost_pm_supervision_pct+in_cost_insurance_other_pct)*G20/MAX(T_Con,1) | H27: =IF(T_Predev>0,C_HardBase*in_cost_design_pct*0.6*H19/T_Predev+C_HardBase*in_cost_design_pct*0.4*H20/MAX(T_Con,1),C_HardBase*in_cost_design_pct*H20/MAX(T_Con,1))+IF(H$4=T_ConStart,C_HardBase*in_cost_permits_pct,0)+C_HardBase*(in_cost_pm_supervision_pct+in_cost_insurance_other_pct)*H20/MAX(T_Con,1) | I27: =IF(T_Predev>0,C_HardBase*in_cost_design_pct*0.6*I19/T_Predev+C_HardBase*in_cost_design_pct*0.4*I20/MAX(T_Con,1),C_HardBase*in_cost_design_pct*I20/MAX(T_Con,1))+IF(I$4=T_ConStart,C_HardBase*in_cost_permits_pct,0)+C_HardBase*(in_cost_pm_supervision_pct+in_cost_insurance_other_pct)*I20/MAX(T_Con,1) | J27: =IF(T_Predev>0,C_HardBase*in_cost_design_pct*0.6*J19/T_Predev+C_HardBase*in_cost_design_pct*0.4*J20/MAX(T_Con,1),C_HardBase*in_cost_design_pct*J20/MAX(T_Con,1))+IF(J$4=T_ConStart,C_HardBase*in_cost_permits_pct,0)+C_HardBase*(in_cost_pm_supervision_pct+in_cost_insurance_other_pct)*J20/MAX(T_Con,1) | K27: =IF(T_Predev>0,C_HardBase*in_cost_design_pct*0.6*K19/T_Predev+C_HardBase*in_cost_design_pct*0.4*K20/MAX(T_Con,1),C_HardBase*in_cost_design_pct*K20/MAX(T_Con,1))+IF(K$4=T_ConStart,C_HardBase*in_cost_permits_pct,0)+C_HardBase*(in_cost_pm_supervision_pct+in_cost_insurance_other_pct)*K20/MAX(T_Con,1) | ... CU27: =IF(T_Predev>0,C_HardBase*in_cost_design_pct*0.6*CU19/T_Predev+C_HardBase*in_cost_design_pct*0.4*CU20/MAX(T_Con,1),C_HardBase*in_cost_design_pct*CU20/MAX(T_Con,1))+IF(CU$4=T_ConStart,C_HardBase*in_cost_permits_pct,0)+C_HardBase*(in_cost_pm_supervision_pct+in_cost_insurance_other_pct)*CU20/MAX(T_Con,1)
A28: Contingency | B28: =SUM(D28:CU28) | D28: =C_Contingency*D21 | E28: =C_Contingency*E21 | F28: =C_Contingency*F21 | G28: =C_Contingency*G21 | H28: =C_Contingency*H21 | I28: =C_Contingency*I21 | J28: =C_Contingency*J21 | K28: =C_Contingency*K21 | ... CU28: =C_Contingency*CU21
A29: Developer fee | B29: =SUM(D29:CU29) | D29: =C_DevFee*D20/MAX(T_Con,1) | E29: =C_DevFee*E20/MAX(T_Con,1) | F29: =C_DevFee*F20/MAX(T_Con,1) | G29: =C_DevFee*G20/MAX(T_Con,1) | H29: =C_DevFee*H20/MAX(T_Con,1) | I29: =C_DevFee*I20/MAX(T_Con,1) | J29: =C_DevFee*J20/MAX(T_Con,1) | K29: =C_DevFee*K20/MAX(T_Con,1) | ... CU29: =C_DevFee*CU20/MAX(T_Con,1)
A30: User-defined variable costs | B30: =SUM(D30:CU30) | D30: =C_CVSpread*D21+SUMPRODUCT((cv_effect="cost_fixed")*(cv_timing="anchor")*(cv_start=D$4)*cv_value)+SUMPRODUCT((cv_effect="cost_monthly")*(cv_start<=D$4)*(cv_end>D$4)*cv_value) | E30: =C_CVSpread*E21+SUMPRODUCT((cv_effect="cost_fixed")*(cv_timing="anchor")*(cv_start=E$4)*cv_value)+SUMPRODUCT((cv_effect="cost_monthly")*(cv_start<=E$4)*(cv_end>E$4)*cv_value) | F30: =C_CVSpread*F21+SUMPRODUCT((cv_effect="cost_fixed")*(cv_timing="anchor")*(cv_start=F$4)*cv_value)+SUMPRODUCT((cv_effect="cost_monthly")*(cv_start<=F$4)*(cv_end>F$4)*cv_value) | G30: =C_CVSpread*G21+SUMPRODUCT((cv_effect="cost_fixed")*(cv_timing="anchor")*(cv_start=G$4)*cv_value)+SUMPRODUCT((cv_effect="cost_monthly")*(cv_start<=G$4)*(cv_end>G$4)*cv_value) | H30: =C_CVSpread*H21+SUMPRODUCT((cv_effect="cost_fixed")*(cv_timing="anchor")*(cv_start=H$4)*cv_value)+SUMPRODUCT((cv_effect="cost_monthly")*(cv_start<=H$4)*(cv_end>H$4)*cv_value) | I30: =C_CVSpread*I21+SUMPRODUCT((cv_effect="cost_fixed")*(cv_timing="anchor")*(cv_start=I$4)*cv_value)+SUMPRODUCT((cv_effect="cost_monthly")*(cv_start<=I$4)*(cv_end>I$4)*cv_value) | J30: =C_CVSpread*J21+SUMPRODUCT((cv_effect="cost_fixed")*(cv_timing="anchor")*(cv_start=J$4)*cv_value)+SUMPRODUCT((cv_effect="cost_monthly")*(cv_start<=J$4)*(cv_end>J$4)*cv_value) | K30: =C_CVSpread*K21+SUMPRODUCT((cv_effect="cost_fixed")*(cv_timing="anchor")*(cv_start=K$4)*cv_value)+SUMPRODUCT((cv_effect="cost_monthly")*(cv_start<=K$4)*(cv_end>K$4)*cv_value) | ... CU30: =C_CVSpread*CU21+SUMPRODUCT((cv_effect="cost_fixed")*(cv_timing="anchor")*(cv_start=CU$4)*cv_value)+SUMPRODUCT((cv_effect="cost_monthly")*(cv_start<=CU$4)*(cv_end>CU$4)*cv_value)
A31: Custom one-off costs | B31: =SUM(D31:CU31) | D31: =SUMPRODUCT((cf_type="cost")*(cf_month=D$4)*cf_amount) | E31: =SUMPRODUCT((cf_type="cost")*(cf_month=E$4)*cf_amount) | F31: =SUMPRODUCT((cf_type="cost")*(cf_month=F$4)*cf_amount) | G31: =SUMPRODUCT((cf_type="cost")*(cf_month=G$4)*cf_amount) | H31: =SUMPRODUCT((cf_type="cost")*(cf_month=H$4)*cf_amount) | I31: =SUMPRODUCT((cf_type="cost")*(cf_month=I$4)*cf_amount) | J31: =SUMPRODUCT((cf_type="cost")*(cf_month=J$4)*cf_amount) | K31: =SUMPRODUCT((cf_type="cost")*(cf_month=K$4)*cf_amount) | ... CU31: =SUMPRODUCT((cf_type="cost")*(cf_month=CU$4)*cf_amount)
A32: Total development costs (before sales costs and financing) | B32: =SUM(D32:CU32) | D32: =D24+D25+D26+D27+D28+D29+D30+D31 | E32: =E24+E25+E26+E27+E28+E29+E30+E31 | F32: =F24+F25+F26+F27+F28+F29+F30+F31 | G32: =G24+G25+G26+G27+G28+G29+G30+G31 | H32: =H24+H25+H26+H27+H28+H29+H30+H31 | I32: =I24+I25+I26+I27+I28+I29+I30+I31 | J32: =J24+J25+J26+J27+J28+J29+J30+J31 | K32: =K24+K25+K26+K27+K28+K29+K30+K31 | ... CU32: =CU24+CU25+CU26+CU27+CU28+CU29+CU30+CU31
A33: Cumulative development costs | D33: =D32 | E33: =E32+D33 | F33: =F32+E33 | G33: =G32+F33 | H33: =H32+G33 | I33: =I32+H33 | J33: =J32+I33 | K33: =K32+J33 | L33: =L32+K33 | ... CU33: =CU32+CT33

Sheet Sales
A1: Sales schedule & cash collections
A2: Units sold per month (phases + base absorption, net of cancellations), contract value and buyer payments
A4: Month | B4: Total | C4: Unit / note | D4: 0 | E4: =D4+1 | F4: =E4+1 | G4: =F4+1 | H4: =G4+1 | I4: =H4+1 | J4: =I4+1 | K4: =J4+1 | L4: =K4+1 | ... CU4: =CT4+1
A5: Base presales start month | B5: =MAX(1,T_ConStart+in_rev_sales_start_offset)
A6: Sales start month (incl. phases) | B6: =MAX(1,MIN(Sales_BaseStart,IF(COUNT(sp_start)>0,MIN(sp_start),Sales_BaseStart)))
A7: Units for sale | B7: =IF(in_mode_sale=1,D_Units,0)
A8: Last month with sales | B8: =SUMPRODUCT(MAX(($D$13:$CU$13>1E-9)*$D$4:$CU$4))
A9: Gross development value (contract value) | B9: =SUM($D$17:$CU$17)
A12: Gross sales pace (units/month) | D12: =IF(D$4<Sales_Start,0,IF(SUMPRODUCT((sp_start<=D$4)*(sp_end>D$4)*1)>0,SUMPRODUCT((sp_start<=D$4)*(sp_end>D$4)*sp_rate)/SUMPRODUCT((sp_start<=D$4)*(sp_end>D$4)*1),in_rev_absorption_per_month)) | E12: =IF(E$4<Sales_Start,0,IF(SUMPRODUCT((sp_start<=E$4)*(sp_end>E$4)*1)>0,SUMPRODUCT((sp_start<=E$4)*(sp_end>E$4)*sp_rate)/SUMPRODUCT((sp_start<=E$4)*(sp_end>E$4)*1),in_rev_absorption_per_month)) | F12: =IF(F$4<Sales_Start,0,IF(SUMPRODUCT((sp_start<=F$4)*(sp_end>F$4)*1)>0,SUMPRODUCT((sp_start<=F$4)*(sp_end>F$4)*sp_rate)/SUMPRODUCT((sp_start<=F$4)*(sp_end>F$4)*1),in_rev_absorption_per_month)) | G12: =IF(G$4<Sales_Start,0,IF(SUMPRODUCT((sp_start<=G$4)*(sp_end>G$4)*1)>0,SUMPRODUCT((sp_start<=G$4)*(sp_end>G$4)*sp_rate)/SUMPRODUCT((sp_start<=G$4)*(sp_end>G$4)*1),in_rev_absorption_per_month)) | H12: =IF(H$4<Sales_Start,0,IF(SUMPRODUCT((sp_start<=H$4)*(sp_end>H$4)*1)>0,SUMPRODUCT((sp_start<=H$4)*(sp_end>H$4)*sp_rate)/SUMPRODUCT((sp_start<=H$4)*(sp_end>H$4)*1),in_rev_absorption_per_month)) | I12: =IF(I$4<Sales_Start,0,IF(SUMPRODUCT((sp_start<=I$4)*(sp_end>I$4)*1)>0,SUMPRODUCT((sp_start<=I$4)*(sp_end>I$4)*sp_rate)/SUMPRODUCT((sp_start<=I$4)*(sp_end>I$4)*1),in_rev_absorption_per_month)) | J12: =IF(J$4<Sales_Start,0,IF(SUMPRODUCT((sp_start<=J$4)*(sp_end>J$4)*1)>0,SUMPRODUCT((sp_start<=J$4)*(sp_end>J$4)*sp_rate)/SUMPRODUCT((sp_start<=J$4)*(sp_end>J$4)*1),in_rev_absorption_per_month)) | K12: =IF(K$4<Sales_Start,0,IF(SUMPRODUCT((sp_start<=K$4)*(sp_end>K$4)*1)>0,SUMPRODUCT((sp_start<=K$4)*(sp_end>K$4)*sp_rate)/SUMPRODUCT((sp_start<=K$4)*(sp_end>K$4)*1),in_rev_absorption_per_month)) | ... CU12: =IF(CU$4<Sales_Start,0,IF(SUMPRODUCT((sp_start<=CU$4)*(sp_end>CU$4)*1)>0,SUMPRODUCT((sp_start<=CU$4)*(sp_end>CU$4)*sp_rate)/SUMPRODUCT((sp_start<=CU$4)*(sp_end>CU$4)*1),in_rev_absorption_per_month))
A13: Units sold (net of cancellations) | B13: =SUM(D13:CU13) | D13: =IF(in_mode_sale=1,MIN(D12*(1-in_rev_cancellation_pct),S_Units),0) | E13: =IF(in_mode_sale=1,MIN(E12*(1-in_rev_cancellation_pct),D14),0) | F13: =IF(in_mode_sale=1,MIN(F12*(1-in_rev_cancellation_pct),E14),0) | G13: =IF(in_mode_sale=1,MIN(G12*(1-in_rev_cancellation_pct),F14),0) | H13: =IF(in_mode_sale=1,MIN(H12*(1-in_rev_cancellation_pct),G14),0) | I13: =IF(in_mode_sale=1,MIN(I12*(1-in_rev_cancellation_pct),H14),0) | J13: =IF(in_mode_sale=1,MIN(J12*(1-in_rev_cancellation_pct),I14),0) | K13: =IF(in_mode_sale=1,MIN(K12*(1-in_rev_cancellation_pct),J14),0) | L13: =IF(in_mode_sale=1,MIN(L12*(1-in_rev_cancellation_pct),K14),0) | ... CU13: =IF(in_mode_sale=1,MIN(CU12*(1-in_rev_cancellation_pct),CT14),0)
A14: Units remaining (end of month) | D14: =S_Units-D13 | E14: =D14-E13 | F14: =E14-F13 | G14: =F14-G13 | H14: =G14-H13 | I14: =H14-I13 | J14: =I14-J13 | K14: =J14-K13 | L14: =K14-L13 | ... CU14: =CT14-CU13
A15: Cumulative units sold | D15: =S_Units-D14 | E15: =S_Units-E14 | F15: =S_Units-F14 | G15: =S_Units-G14 | H15: =S_Units-H14 | I15: =S_Units-I14 | J15: =S_Units-J14 | K15: =S_Units-K14 | ... CU15: =S_Units-CU14
A16: Price phase multiplier | D16: =EXP(SUMPRODUCT((pp_start<=D$4)*(pp_end>D$4)*LN(1+pp_pct))) | E16: =EXP(SUMPRODUCT((pp_start<=E$4)*(pp_end>E$4)*LN(1+pp_pct))) | F16: =EXP(SUMPRODUCT((pp_start<=F$4)*(pp_end>F$4)*LN(1+pp_pct))) | G16: =EXP(SUMPRODUCT((pp_start<=G$4)*(pp_end>G$4)*LN(1+pp_pct))) | H16: =EXP(SUMPRODUCT((pp_start<=H$4)*(pp_end>H$4)*LN(1+pp_pct))) | I16: =EXP(SUMPRODUCT((pp_start<=I$4)*(pp_end>I$4)*LN(1+pp_pct))) | J16: =EXP(SUMPRODUCT((pp_start<=J$4)*(pp_end>J$4)*LN(1+pp_pct))) | K16: =EXP(SUMPRODUCT((pp_start<=K$4)*(pp_end>K$4)*LN(1+pp_pct))) | ... CU16: =EXP(SUMPRODUCT((pp_start<=CU$4)*(pp_end>CU$4)*LN(1+pp_pct)))
A17: Contract value signed | B17: =SUM(D17:CU17) | D17: =D13*D_AvgPrice*(1+in_rev_escalation_pct)^(D$4/12)*(1-in_rev_discount_pct)*D16 | E17: =E13*D_AvgPrice*(1+in_rev_escalation_pct)^(E$4/12)*(1-in_rev_discount_pct)*E16 | F17: =F13*D_AvgPrice*(1+in_rev_escalation_pct)^(F$4/12)*(1-in_rev_discount_pct)*F16 | G17: =G13*D_AvgPrice*(1+in_rev_escalation_pct)^(G$4/12)*(1-in_rev_discount_pct)*G16 | H17: =H13*D_AvgPrice*(1+in_rev_escalation_pct)^(H$4/12)*(1-in_rev_discount_pct)*H16 | I17: =I13*D_AvgPrice*(1+in_rev_escalation_pct)^(I$4/12)*(1-in_rev_discount_pct)*I16 | J17: =J13*D_AvgPrice*(1+in_rev_escalation_pct)^(J$4/12)*(1-in_rev_discount_pct)*J16 | K17: =K13*D_AvgPrice*(1+in_rev_escalation_pct)^(K$4/12)*(1-in_rev_discount_pct)*K16 | ... CU17: =CU13*D_AvgPrice*(1+in_rev_escalation_pct)^(CU$4/12)*(1-in_rev_discount_pct)*CU16
A18: Cash collections (buyer payment plan)
A19: Deposits | B19: =SUM(D19:CU19) | D19: =IF(D$4<T_Delivery,D17*in_rev_deposit_pct,0) | E19: =IF(E$4<T_Delivery,E17*in_rev_deposit_pct,0) | F19: =IF(F$4<T_Delivery,F17*in_rev_deposit_pct,0) | G19: =IF(G$4<T_Delivery,G17*in_rev_deposit_pct,0) | H19: =IF(H$4<T_Delivery,H17*in_rev_deposit_pct,0) | I19: =IF(I$4<T_Delivery,I17*in_rev_deposit_pct,0) | J19: =IF(J$4<T_Delivery,J17*in_rev_deposit_pct,0) | K19: =IF(K$4<T_Delivery,K17*in_rev_deposit_pct,0) | ... CU19: =IF(CU$4<T_Delivery,CU17*in_rev_deposit_pct,0)
A20: Installment per month generated by this month's sales (helper) | D20: =IF(AND(D$4<T_Delivery,T_Delivery-D$4-1>0),D17*in_rev_installments_pct/(T_Delivery-D$4-1),0) | E20: =IF(AND(E$4<T_Delivery,T_Delivery-E$4-1>0),E17*in_rev_installments_pct/(T_Delivery-E$4-1),0) | F20: =IF(AND(F$4<T_Delivery,T_Delivery-F$4-1>0),F17*in_rev_installments_pct/(T_Delivery-F$4-1),0) | G20: =IF(AND(G$4<T_Delivery,T_Delivery-G$4-1>0),G17*in_rev_installments_pct/(T_Delivery-G$4-1),0) | H20: =IF(AND(H$4<T_Delivery,T_Delivery-H$4-1>0),H17*in_rev_installments_pct/(T_Delivery-H$4-1),0) | I20: =IF(AND(I$4<T_Delivery,T_Delivery-I$4-1>0),I17*in_rev_installments_pct/(T_Delivery-I$4-1),0) | J20: =IF(AND(J$4<T_Delivery,T_Delivery-J$4-1>0),J17*in_rev_installments_pct/(T_Delivery-J$4-1),0) | K20: =IF(AND(K$4<T_Delivery,T_Delivery-K$4-1>0),K17*in_rev_installments_pct/(T_Delivery-K$4-1),0) | ... CU20: =IF(AND(CU$4<T_Delivery,T_Delivery-CU$4-1>0),CU17*in_rev_installments_pct/(T_Delivery-CU$4-1),0)
A21: Construction-stage installments | B21: =SUM(D21:CU21) | D21: =IF(D$4<T_Delivery,SUMPRODUCT(($D$4:$CU$4<D$4)*$D$20:$CU$20),0) | E21: =IF(E$4<T_Delivery,SUMPRODUCT(($D$4:$CU$4<E$4)*$D$20:$CU$20),0) | F21: =IF(F$4<T_Delivery,SUMPRODUCT(($D$4:$CU$4<F$4)*$D$20:$CU$20),0) | G21: =IF(G$4<T_Delivery,SUMPRODUCT(($D$4:$CU$4<G$4)*$D$20:$CU$20),0) | H21: =IF(H$4<T_Delivery,SUMPRODUCT(($D$4:$CU$4<H$4)*$D$20:$CU$20),0) | I21: =IF(I$4<T_Delivery,SUMPRODUCT(($D$4:$CU$4<I$4)*$D$20:$CU$20),0) | J21: =IF(J$4<T_Delivery,SUMPRODUCT(($D$4:$CU$4<J$4)*$D$20:$CU$20),0) | K21: =IF(K$4<T_Delivery,SUMPRODUCT(($D$4:$CU$4<K$4)*$D$20:$CU$20),0) | ... CU21: =IF(CU$4<T_Delivery,SUMPRODUCT(($D$4:$CU$4<CU$4)*$D$20:$CU$20),0)
A22: Balance at delivery (closing) | B22: =SUM(D22:CU22) | D22: =IF(D$4=T_Delivery,in_rev_closing_pct*SUMPRODUCT(($D$4:$CU$4<T_Delivery)*$D$17:$CU$17)+in_rev_installments_pct*SUMPRODUCT(($D$4:$CU$4=T_Delivery-1)*$D$17:$CU$17),0) | E22: =IF(E$4=T_Delivery,in_rev_closing_pct*SUMPRODUCT(($D$4:$CU$4<T_Delivery)*$D$17:$CU$17)+in_rev_installments_pct*SUMPRODUCT(($D$4:$CU$4=T_Delivery-1)*$D$17:$CU$17),0) | F22: =IF(F$4=T_Delivery,in_rev_closing_pct*SUMPRODUCT(($D$4:$CU$4<T_Delivery)*$D$17:$CU$17)+in_rev_installments_pct*SUMPRODUCT(($D$4:$CU$4=T_Delivery-1)*$D$17:$CU$17),0) | G22: =IF(G$4=T_Delivery,in_rev_closing_pct*SUMPRODUCT(($D$4:$CU$4<T_Delivery)*$D$17:$CU$17)+in_rev_installments_pct*SUMPRODUCT(($D$4:$CU$4=T_Delivery-1)*$D$17:$CU$17),0) | H22: =IF(H$4=T_Delivery,in_rev_closing_pct*SUMPRODUCT(($D$4:$CU$4<T_Delivery)*$D$17:$CU$17)+in_rev_installments_pct*SUMPRODUCT(($D$4:$CU$4=T_Delivery-1)*$D$17:$CU$17),0) | I22: =IF(I$4=T_Delivery,in_rev_closing_pct*SUMPRODUCT(($D$4:$CU$4<T_Delivery)*$D$17:$CU$17)+in_rev_installments_pct*SUMPRODUCT(($D$4:$CU$4=T_Delivery-1)*$D$17:$CU$17),0) | J22: =IF(J$4=T_Delivery,in_rev_closing_pct*SUMPRODUCT(($D$4:$CU$4<T_Delivery)*$D$17:$CU$17)+in_rev_installments_pct*SUMPRODUCT(($D$4:$CU$4=T_Delivery-1)*$D$17:$CU$17),0) | K22: =IF(K$4=T_Delivery,in_rev_closing_pct*SUMPRODUCT(($D$4:$CU$4<T_Delivery)*$D$17:$CU$17)+in_rev_installments_pct*SUMPRODUCT(($D$4:$CU$4=T_Delivery-1)*$D$17:$CU$17),0) | ... CU22: =IF(CU$4=T_Delivery,in_rev_closing_pct*SUMPRODUCT(($D$4:$CU$4<T_Delivery)*$D$17:$CU$17)+in_rev_installments_pct*SUMPRODUCT(($D$4:$CU$4=T_Delivery-1)*$D$17:$CU$17),0)
A23: Sales after delivery (paid in full) | B23: =SUM(D23:CU23) | D23: =IF(D$4>=T_Delivery,D17,0) | E23: =IF(E$4>=T_Delivery,E17,0) | F23: =IF(F$4>=T_Delivery,F17,0) | G23: =IF(G$4>=T_Delivery,G17,0) | H23: =IF(H$4>=T_Delivery,H17,0) | I23: =IF(I$4>=T_Delivery,I17,0) | J23: =IF(J$4>=T_Delivery,J17,0) | K23: =IF(K$4>=T_Delivery,K17,0) | ... CU23: =IF(CU$4>=T_Delivery,CU17,0)
A24: User-defined income per unit sold | B24: =SUM(D24:CU24) | D24: =D13*SUMPRODUCT((cv_effect="revenue_per_unit")*cv_value) | E24: =E13*SUMPRODUCT((cv_effect="revenue_per_unit")*cv_value) | F24: =F13*SUMPRODUCT((cv_effect="revenue_per_unit")*cv_value) | G24: =G13*SUMPRODUCT((cv_effect="revenue_per_unit")*cv_value) | H24: =H13*SUMPRODUCT((cv_effect="revenue_per_unit")*cv_value) | I24: =I13*SUMPRODUCT((cv_effect="revenue_per_unit")*cv_value) | J24: =J13*SUMPRODUCT((cv_effect="revenue_per_unit")*cv_value) | K24: =K13*SUMPRODUCT((cv_effect="revenue_per_unit")*cv_value) | ... CU24: =CU13*SUMPRODUCT((cv_effect="revenue_per_unit")*cv_value)
A25: Total sales collections | B25: =SUM(D25:CU25) | D25: =D19+D21+D22+D23 | E25: =E19+E21+E22+E23 | F25: =F19+F21+F22+F23 | G25: =G19+G21+G22+G23 | H25: =H19+H21+H22+H23 | I25: =I19+I21+I22+I23 | J25: =J19+J21+J22+J23 | K25: =K19+K21+K22+K23 | ... CU25: =CU19+CU21+CU22+CU23
A26: Sales costs
A27: Sales commissions (paid at contract) | B27: =SUM(D27:CU27) | D27: =D17*in_rev_commission_pct | E27: =E17*in_rev_commission_pct | F27: =F17*in_rev_commission_pct | G27: =G17*in_rev_commission_pct | H27: =H17*in_rev_commission_pct | I27: =I17*in_rev_commission_pct | J27: =J17*in_rev_commission_pct | K27: =K17*in_rev_commission_pct | ... CU27: =CU17*in_rev_commission_pct
A28: Marketing & sales office | B28: =SUM(D28:CU28) | D28: =IF(AND(D$4>=Sales_Start,D$4<=Sales_Last),S_GDV*in_rev_marketing_pct/(Sales_Last-Sales_Start+1),0) | E28: =IF(AND(E$4>=Sales_Start,E$4<=Sales_Last),S_GDV*in_rev_marketing_pct/(Sales_Last-Sales_Start+1),0) | F28: =IF(AND(F$4>=Sales_Start,F$4<=Sales_Last),S_GDV*in_rev_marketing_pct/(Sales_Last-Sales_Start+1),0) | G28: =IF(AND(G$4>=Sales_Start,G$4<=Sales_Last),S_GDV*in_rev_marketing_pct/(Sales_Last-Sales_Start+1),0) | H28: =IF(AND(H$4>=Sales_Start,H$4<=Sales_Last),S_GDV*in_rev_marketing_pct/(Sales_Last-Sales_Start+1),0) | I28: =IF(AND(I$4>=Sales_Start,I$4<=Sales_Last),S_GDV*in_rev_marketing_pct/(Sales_Last-Sales_Start+1),0) | J28: =IF(AND(J$4>=Sales_Start,J$4<=Sales_Last),S_GDV*in_rev_marketing_pct/(Sales_Last-Sales_Start+1),0) | K28: =IF(AND(K$4>=Sales_Start,K$4<=Sales_Last),S_GDV*in_rev_marketing_pct/(Sales_Last-Sales_Start+1),0) | ... CU28: =IF(AND(CU$4>=Sales_Start,CU$4<=Sales_Last),S_GDV*in_rev_marketing_pct/(Sales_Last-Sales_Start+1),0)
A29: User-defined % of collections (e.g. trust fees) | B29: =SUM(D29:CU29) | D29: =D25*SUMPRODUCT((cv_effect="cost_pct_revenue")*cv_value) | E29: =E25*SUMPRODUCT((cv_effect="cost_pct_revenue")*cv_value) | F29: =F25*SUMPRODUCT((cv_effect="cost_pct_revenue")*cv_value) | G29: =G25*SUMPRODUCT((cv_effect="cost_pct_revenue")*cv_value) | H29: =H25*SUMPRODUCT((cv_effect="cost_pct_revenue")*cv_value) | I29: =I25*SUMPRODUCT((cv_effect="cost_pct_revenue")*cv_value) | J29: =J25*SUMPRODUCT((cv_effect="cost_pct_revenue")*cv_value) | K29: =K25*SUMPRODUCT((cv_effect="cost_pct_revenue")*cv_value) | ... CU29: =CU25*SUMPRODUCT((cv_effect="cost_pct_revenue")*cv_value)
A30: Total sales costs | B30: =SUM(D30:CU30) | D30: =D27+D28+D29 | E30: =E27+E28+E29 | F30: =F27+F28+F29 | G30: =G27+G28+G29 | H30: =H27+H28+H29 | I30: =I27+I28+I29 | J30: =J27+J28+J29 | K30: =K27+K28+K29 | ... CU30: =CU27+CU28+CU29

Sheet Rental
A1: Rental operations & exit
A2: GPR − vacancy − concessions = EGI; EGI − opex (+ owner savings) = NOI; exit on forward NOI / cap rate
A4: Month | B4: Total | C4: Unit / note | D4: 0 | E4: =D4+1 | F4: =E4+1 | G4: =F4+1 | H4: =G4+1 | I4: =H4+1 | J4: =I4+1 | K4: =J4+1 | L4: =K4+1 | ... CU4: =CT4+1
A5: Lease-up starts (month) | B5: =IF(in_ground_up=1,T_Delivery+1,1)
A6: Exit month | B6: =IF(in_ground_up=1,T_Delivery,0)+in_rent_hold_years*12
A7: Effective rent per m²/month | B7: =IF(in_mode_sale=0,in_rent_rent_per_area_month,0)*(1+in_green_rent_prem)*CV_PriceMult
A8: Monthly rent growth factor q | B8: =(1+in_rent_growth_pct)^(1/12)
A9: Forward 12-month stabilized NOI at exit | B9: =(D_Saleable*R_Rent*(1-in_rent_vacancy_pct)*(1-in_rent_concessions_pct)*(1-in_rent_opex_pct_egi)+in_green_savings/12)*IF(R_q=1,12,R_q^R_Exit*R_q*(R_q^12-1)/(R_q-1))
A10: Exit value (gross) | B10: =IF(in_mode_sale=0,IF(in_rent_exit_cap_pct>0,R_FwdNOI/in_rent_exit_cap_pct,0),0)
A11: Stabilized NOI (annual) | B11: =12*(D_Saleable*R_Rent*(1+in_rent_growth_pct)^((R_Start+IF(in_ground_up=1,in_rent_lease_up_months,0))/12)*(1-in_rent_vacancy_pct)*(1-in_rent_concessions_pct)*(1-in_rent_opex_pct_egi)+in_green_savings/12*(1+in_rent_growth_pct)^((R_Start+IF(in_ground_up=1,in_rent_lease_up_months,0))/12))
A14: Occupancy | D14: =IF(OR(in_mode_sale=1,D$4<R_Start,D$4>R_Exit),0,IF(AND(in_ground_up=1,in_rent_lease_up_months>0,D$4-R_Start<in_rent_lease_up_months),(1-in_rent_vacancy_pct)*(D$4-R_Start+1)/in_rent_lease_up_months,1-in_rent_vacancy_pct)) | E14: =IF(OR(in_mode_sale=1,E$4<R_Start,E$4>R_Exit),0,IF(AND(in_ground_up=1,in_rent_lease_up_months>0,E$4-R_Start<in_rent_lease_up_months),(1-in_rent_vacancy_pct)*(E$4-R_Start+1)/in_rent_lease_up_months,1-in_rent_vacancy_pct)) | F14: =IF(OR(in_mode_sale=1,F$4<R_Start,F$4>R_Exit),0,IF(AND(in_ground_up=1,in_rent_lease_up_months>0,F$4-R_Start<in_rent_lease_up_months),(1-in_rent_vacancy_pct)*(F$4-R_Start+1)/in_rent_lease_up_months,1-in_rent_vacancy_pct)) | G14: =IF(OR(in_mode_sale=1,G$4<R_Start,G$4>R_Exit),0,IF(AND(in_ground_up=1,in_rent_lease_up_months>0,G$4-R_Start<in_rent_lease_up_months),(1-in_rent_vacancy_pct)*(G$4-R_Start+1)/in_rent_lease_up_months,1-in_rent_vacancy_pct)) | H14: =IF(OR(in_mode_sale=1,H$4<R_Start,H$4>R_Exit),0,IF(AND(in_ground_up=1,in_rent_lease_up_months>0,H$4-R_Start<in_rent_lease_up_months),(1-in_rent_vacancy_pct)*(H$4-R_Start+1)/in_rent_lease_up_months,1-in_rent_vacancy_pct)) | I14: =IF(OR(in_mode_sale=1,I$4<R_Start,I$4>R_Exit),0,IF(AND(in_ground_up=1,in_rent_lease_up_months>0,I$4-R_Start<in_rent_lease_up_months),(1-in_rent_vacancy_pct)*(I$4-R_Start+1)/in_rent_lease_up_months,1-in_rent_vacancy_pct)) | J14: =IF(OR(in_mode_sale=1,J$4<R_Start,J$4>R_Exit),0,IF(AND(in_ground_up=1,in_rent_lease_up_months>0,J$4-R_Start<in_rent_lease_up_months),(1-in_rent_vacancy_pct)*(J$4-R_Start+1)/in_rent_lease_up_months,1-in_rent_vacancy_pct)) | K14: =IF(OR(in_mode_sale=1,K$4<R_Start,K$4>R_Exit),0,IF(AND(in_ground_up=1,in_rent_lease_up_months>0,K$4-R_Start<in_rent_lease_up_months),(1-in_rent_vacancy_pct)*(K$4-R_Start+1)/in_rent_lease_up_months,1-in_rent_vacancy_pct)) | ... CU14: =IF(OR(in_mode_sale=1,CU$4<R_Start,CU$4>R_Exit),0,IF(AND(in_ground_up=1,in_rent_lease_up_months>0,CU$4-R_Start<in_rent_lease_up_months),(1-in_rent_vacancy_pct)*(CU$4-R_Start+1)/in_rent_lease_up_months,1-in_rent_vacancy_pct))
A15: Gross potential rent | B15: =SUM(D15:CU15) | D15: =IF(OR(in_mode_sale=1,D$4<R_Start,D$4>R_Exit),0,D_Saleable*R_Rent*(1+in_rent_growth_pct)^(D$4/12)) | E15: =IF(OR(in_mode_sale=1,E$4<R_Start,E$4>R_Exit),0,D_Saleable*R_Rent*(1+in_rent_growth_pct)^(E$4/12)) | F15: =IF(OR(in_mode_sale=1,F$4<R_Start,F$4>R_Exit),0,D_Saleable*R_Rent*(1+in_rent_growth_pct)^(F$4/12)) | G15: =IF(OR(in_mode_sale=1,G$4<R_Start,G$4>R_Exit),0,D_Saleable*R_Rent*(1+in_rent_growth_pct)^(G$4/12)) | H15: =IF(OR(in_mode_sale=1,H$4<R_Start,H$4>R_Exit),0,D_Saleable*R_Rent*(1+in_rent_growth_pct)^(H$4/12)) | I15: =IF(OR(in_mode_sale=1,I$4<R_Start,I$4>R_Exit),0,D_Saleable*R_Rent*(1+in_rent_growth_pct)^(I$4/12)) | J15: =IF(OR(in_mode_sale=1,J$4<R_Start,J$4>R_Exit),0,D_Saleable*R_Rent*(1+in_rent_growth_pct)^(J$4/12)) | K15: =IF(OR(in_mode_sale=1,K$4<R_Start,K$4>R_Exit),0,D_Saleable*R_Rent*(1+in_rent_growth_pct)^(K$4/12)) | ... CU15: =IF(OR(in_mode_sale=1,CU$4<R_Start,CU$4>R_Exit),0,D_Saleable*R_Rent*(1+in_rent_growth_pct)^(CU$4/12))
A16: Effective gross income | B16: =SUM(D16:CU16) | D16: =D15*D14*(1-in_rent_concessions_pct) | E16: =E15*E14*(1-in_rent_concessions_pct) | F16: =F15*F14*(1-in_rent_concessions_pct) | G16: =G15*G14*(1-in_rent_concessions_pct) | H16: =H15*H14*(1-in_rent_concessions_pct) | I16: =I15*I14*(1-in_rent_concessions_pct) | J16: =J15*J14*(1-in_rent_concessions_pct) | K16: =K15*K14*(1-in_rent_concessions_pct) | ... CU16: =CU15*CU14*(1-in_rent_concessions_pct)
A17: Operating expenses (net of owner savings) | B17: =SUM(D17:CU17) | D17: =IF(OR(in_mode_sale=1,D$4<R_Start,D$4>R_Exit),0,D16*in_rent_opex_pct_egi-in_green_savings/12*(1+in_rent_growth_pct)^(D$4/12)) | E17: =IF(OR(in_mode_sale=1,E$4<R_Start,E$4>R_Exit),0,E16*in_rent_opex_pct_egi-in_green_savings/12*(1+in_rent_growth_pct)^(E$4/12)) | F17: =IF(OR(in_mode_sale=1,F$4<R_Start,F$4>R_Exit),0,F16*in_rent_opex_pct_egi-in_green_savings/12*(1+in_rent_growth_pct)^(F$4/12)) | G17: =IF(OR(in_mode_sale=1,G$4<R_Start,G$4>R_Exit),0,G16*in_rent_opex_pct_egi-in_green_savings/12*(1+in_rent_growth_pct)^(G$4/12)) | H17: =IF(OR(in_mode_sale=1,H$4<R_Start,H$4>R_Exit),0,H16*in_rent_opex_pct_egi-in_green_savings/12*(1+in_rent_growth_pct)^(H$4/12)) | I17: =IF(OR(in_mode_sale=1,I$4<R_Start,I$4>R_Exit),0,I16*in_rent_opex_pct_egi-in_green_savings/12*(1+in_rent_growth_pct)^(I$4/12)) | J17: =IF(OR(in_mode_sale=1,J$4<R_Start,J$4>R_Exit),0,J16*in_rent_opex_pct_egi-in_green_savings/12*(1+in_rent_growth_pct)^(J$4/12)) | K17: =IF(OR(in_mode_sale=1,K$4<R_Start,K$4>R_Exit),0,K16*in_rent_opex_pct_egi-in_green_savings/12*(1+in_rent_growth_pct)^(K$4/12)) | ... CU17: =IF(OR(in_mode_sale=1,CU$4<R_Start,CU$4>R_Exit),0,CU16*in_rent_opex_pct_egi-in_green_savings/12*(1+in_rent_growth_pct)^(CU$4/12))
A18: Net operating income | B18: =SUM(D18:CU18) | D18: =D16-D17 | E18: =E16-E17 | F18: =F16-F17 | G18: =G16-G17 | H18: =H16-H17 | I18: =I16-I17 | J18: =J16-J17 | K18: =K16-K17 | ... CU18: =CU16-CU17
A19: Exit proceeds (net of selling costs) | B19: =SUM(D19:CU19) | D19: =IF(AND(in_mode_sale=0,D$4=R_Exit),R_ExitValue*(1-in_rent_selling_costs_pct),0) | E19: =IF(AND(in_mode_sale=0,E$4=R_Exit),R_ExitValue*(1-in_rent_selling_costs_pct),0) | F19: =IF(AND(in_mode_sale=0,F$4=R_Exit),R_ExitValue*(1-in_rent_selling_costs_pct),0) | G19: =IF(AND(in_mode_sale=0,G$4=R_Exit),R_ExitValue*(1-in_rent_selling_costs_pct),0) | H19: =IF(AND(in_mode_sale=0,H$4=R_Exit),R_ExitValue*(1-in_rent_selling_costs_pct),0) | I19: =IF(AND(in_mode_sale=0,I$4=R_Exit),R_ExitValue*(1-in_rent_selling_costs_pct),0) | J19: =IF(AND(in_mode_sale=0,J$4=R_Exit),R_ExitValue*(1-in_rent_selling_costs_pct),0) | K19: =IF(AND(in_mode_sale=0,K$4=R_Exit),R_ExitValue*(1-in_rent_selling_costs_pct),0) | ... CU19: =IF(AND(in_mode_sale=0,CU$4=R_Exit),R_ExitValue*(1-in_rent_selling_costs_pct),0)
A20: Total operating & exit inflows | B20: =SUM(D20:CU20) | D20: =D18+D19 | E20: =E18+E19 | F20: =F18+F19 | G20: =G18+G19 | H20: =H18+H19 | I20: =I18+I19 | J20: =J18+J19 | K20: =K18+K19 | ... CU20: =CU18+CU19

Sheet Cash Flow
A1: Cash flow & financing
A2: Unlevered cash flow, then equity first → mezzanine → senior debt; interest on the actual monthly balance
A4: Month | B4: Total | C4: Unit / note | D4: 0 | E4: =D4+1 | F4: =E4+1 | G4: =F4+1 | H4: =G4+1 | I4: =H4+1 | J4: =I4+1 | K4: =J4+1 | L4: =K4+1 | ... CU4: =CT4+1
A5: End month (last cash flow) | B5: =MAX(IF(in_mode_sale=1,MAX(T_Delivery,Sales_Last),R_Exit),IF(COUNT(cf_month)>0,MAX(cf_month),0),SUMPRODUCT(MAX((Construction!$D$32:$CU$32<>0)*$D$4:$CU$4)))
A6: Total development cost (TDC, excl. financing) | B6: =SUM($D$22:$CU$22)
A7: Financing cost (interest + fees) | B7: =B30+B32+B33
A8: Total cost incl. financing | B8: =TDC+FinCost
A9: Senior rate (annual, nominal) | B9: =IF(in_fin_senior_rate_type="fixed",N(in_fin_senior_fixed_rate_pct),N(in_fin_reference_rate_pct)+in_fin_senior_spread_pct)
A10: Senior commitment (LTC × cost incl. financing) | B10: =in_fin_senior_ltc_pct*(TDC+FinCostSizing) | C10: Circular by design (debt sized on cost incl. financing). Iterative calculation is on; set the circuit breaker on Assumptions to 0 to break the loop.
A11: Mezzanine commitment | B11: =N(in_fin_mezz_ltc_pct)*(TDC+FinCostSizing)
A12: Planned equity (cap before debt) | B12: =MAX(TDC+FinCostSizing-F_SeniorCommit-F_MezzCommit,0)
A13: Fixed monthly principal after delivery (rentals) | B13: =IF(N(in_fin_amortization_years)>0,INDEX($D$56:$CU$56,1,T_Delivery+1)*IF(F_SeniorRate/12=0,1/(in_fin_amortization_years*12),F_SeniorRate/12/(1-(1+F_SeniorRate/12)^-(in_fin_amortization_years*12)))-INDEX($D$56:$CU$56,1,T_Delivery+1)*F_SeniorRate/12,0)
A14: Financing cost used for debt sizing (circuit breaker) | B14: =IF(in_circ_switch=1,IFERROR(FinCost,0),0)
A17: End month (flag) | D17: =IF(D$4=T_End,1,0) | E17: =IF(E$4=T_End,1,0) | F17: =IF(F$4=T_End,1,0) | G17: =IF(G$4=T_End,1,0) | H17: =IF(H$4=T_End,1,0) | I17: =IF(I$4=T_End,1,0) | J17: =IF(J$4=T_End,1,0) | K17: =IF(K$4=T_End,1,0) | ... CU17: =IF(CU$4=T_End,1,0)
A18: On or after delivery (flag) | D18: =IF(OR(D$4>=T_Delivery,D$4=T_End),1,0) | E18: =IF(OR(E$4>=T_Delivery,E$4=T_End),1,0) | F18: =IF(OR(F$4>=T_Delivery,F$4=T_End),1,0) | G18: =IF(OR(G$4>=T_Delivery,G$4=T_End),1,0) | H18: =IF(OR(H$4>=T_Delivery,H$4=T_End),1,0) | I18: =IF(OR(I$4>=T_Delivery,I$4=T_End),1,0) | J18: =IF(OR(J$4>=T_Delivery,J$4=T_End),1,0) | K18: =IF(OR(K$4>=T_Delivery,K$4=T_End),1,0) | ... CU18: =IF(OR(CU$4>=T_Delivery,CU$4=T_End),1,0)
A19: Unlevered cash flow
A20: Development costs | B20: =SUM(D20:CU20) | D20: =Construction!D32 | E20: =Construction!E32 | F20: =Construction!F32 | G20: =Construction!G32 | H20: =Construction!H32 | I20: =Construction!I32 | J20: =Construction!J32 | K20: =Construction!K32 | ... CU20: =Construction!CU32
A21: Sales costs | B21: =SUM(D21:CU21) | D21: =IF(in_mode_sale=1,Sales!D30,0) | E21: =IF(in_mode_sale=1,Sales!E30,0) | F21: =IF(in_mode_sale=1,Sales!F30,0) | G21: =IF(in_mode_sale=1,Sales!G30,0) | H21: =IF(in_mode_sale=1,Sales!H30,0) | I21: =IF(in_mode_sale=1,Sales!I30,0) | J21: =IF(in_mode_sale=1,Sales!J30,0) | K21: =IF(in_mode_sale=1,Sales!K30,0) | ... CU21: =IF(in_mode_sale=1,Sales!CU30,0)
A22: Total outflows | B22: =SUM(D22:CU22) | D22: =IF(D$4>T_End,0,D20+D21) | E22: =IF(E$4>T_End,0,E20+E21) | F22: =IF(F$4>T_End,0,F20+F21) | G22: =IF(G$4>T_End,0,G20+G21) | H22: =IF(H$4>T_End,0,H20+H21) | I22: =IF(I$4>T_End,0,I20+I21) | J22: =IF(J$4>T_End,0,J20+J21) | K22: =IF(K$4>T_End,0,K20+K21) | ... CU22: =IF(CU$4>T_End,0,CU20+CU21)
A23: Sales collections / operating income | B23: =SUM(D23:CU23) | D23: =IF(in_mode_sale=1,Sales!D25+Sales!D24,Rental!D20) | E23: =IF(in_mode_sale=1,Sales!E25+Sales!E24,Rental!E20) | F23: =IF(in_mode_sale=1,Sales!F25+Sales!F24,Rental!F20) | G23: =IF(in_mode_sale=1,Sales!G25+Sales!G24,Rental!G20) | H23: =IF(in_mode_sale=1,Sales!H25+Sales!H24,Rental!H20) | I23: =IF(in_mode_sale=1,Sales!I25+Sales!I24,Rental!I20) | J23: =IF(in_mode_sale=1,Sales!J25+Sales!J24,Rental!J20) | K23: =IF(in_mode_sale=1,Sales!K25+Sales!K24,Rental!K20) | ... CU23: =IF(in_mode_sale=1,Sales!CU25+Sales!CU24,Rental!CU20)
A24: Other income (custom flows & user-defined) | B24: =SUM(D24:CU24) | D24: =SUMPRODUCT((cf_type="revenue")*(cf_month=D$4)*cf_amount)+SUMPRODUCT((cv_effect="revenue_fixed")*(cv_start=D$4)*cv_value)+SUMPRODUCT((cv_effect="revenue_monthly")*(cv_start<=D$4)*(cv_end>D$4)*cv_value)+IF(AND(in_mode_sale=0,D$4=R_Start),D_Units*SUMPRODUCT((cv_effect="revenue_per_unit")*cv_value),0) | E24: =SUMPRODUCT((cf_type="revenue")*(cf_month=E$4)*cf_amount)+SUMPRODUCT((cv_effect="revenue_fixed")*(cv_start=E$4)*cv_value)+SUMPRODUCT((cv_effect="revenue_monthly")*(cv_start<=E$4)*(cv_end>E$4)*cv_value)+IF(AND(in_mode_sale=0,E$4=R_Start),D_Units*SUMPRODUCT((cv_effect="revenue_per_unit")*cv_value),0) | F24: =SUMPRODUCT((cf_type="revenue")*(cf_month=F$4)*cf_amount)+SUMPRODUCT((cv_effect="revenue_fixed")*(cv_start=F$4)*cv_value)+SUMPRODUCT((cv_effect="revenue_monthly")*(cv_start<=F$4)*(cv_end>F$4)*cv_value)+IF(AND(in_mode_sale=0,F$4=R_Start),D_Units*SUMPRODUCT((cv_effect="revenue_per_unit")*cv_value),0) | G24: =SUMPRODUCT((cf_type="revenue")*(cf_month=G$4)*cf_amount)+SUMPRODUCT((cv_effect="revenue_fixed")*(cv_start=G$4)*cv_value)+SUMPRODUCT((cv_effect="revenue_monthly")*(cv_start<=G$4)*(cv_end>G$4)*cv_value)+IF(AND(in_mode_sale=0,G$4=R_Start),D_Units*SUMPRODUCT((cv_effect="revenue_per_unit")*cv_value),0) | H24: =SUMPRODUCT((cf_type="revenue")*(cf_month=H$4)*cf_amount)+SUMPRODUCT((cv_effect="revenue_fixed")*(cv_start=H$4)*cv_value)+SUMPRODUCT((cv_effect="revenue_monthly")*(cv_start<=H$4)*(cv_end>H$4)*cv_value)+IF(AND(in_mode_sale=0,H$4=R_Start),D_Units*SUMPRODUCT((cv_effect="revenue_per_unit")*cv_value),0) | I24: =SUMPRODUCT((cf_type="revenue")*(cf_month=I$4)*cf_amount)+SUMPRODUCT((cv_effect="revenue_fixed")*(cv_start=I$4)*cv_value)+SUMPRODUCT((cv_effect="revenue_monthly")*(cv_start<=I$4)*(cv_end>I$4)*cv_value)+IF(AND(in_mode_sale=0,I$4=R_Start),D_Units*SUMPRODUCT((cv_effect="revenue_per_unit")*cv_value),0) | J24: =SUMPRODUCT((cf_type="revenue")*(cf_month=J$4)*cf_amount)+SUMPRODUCT((cv_effect="revenue_fixed")*(cv_start=J$4)*cv_value)+SUMPRODUCT((cv_effect="revenue_monthly")*(cv_start<=J$4)*(cv_end>J$4)*cv_value)+IF(AND(in_mode_sale=0,J$4=R_Start),D_Units*SUMPRODUCT((cv_effect="revenue_per_unit")*cv_value),0) | K24: =SUMPRODUCT((cf_type="revenue")*(cf_month=K$4)*cf_amount)+SUMPRODUCT((cv_effect="revenue_fixed")*(cv_start=K$4)*cv_value)+SUMPRODUCT((cv_effect="revenue_monthly")*(cv_start<=K$4)*(cv_end>K$4)*cv_value)+IF(AND(in_mode_sale=0,K$4=R_Start),D_Units*SUMPRODUCT((cv_effect="revenue_per_unit")*cv_value),0) | ... CU24: =SUMPRODUCT((cf_type="revenue")*(cf_month=CU$4)*cf_amount)+SUMPRODUCT((cv_effect="revenue_fixed")*(cv_start=CU$4)*cv_value)+SUMPRODUCT((cv_effect="revenue_monthly")*(cv_start<=CU$4)*(cv_end>CU$4)*cv_value)+IF(AND(in_mode_sale=0,CU$4=R_Start),D_Units*SUMPRODUCT((cv_effect="revenue_per_unit")*cv_value),0)
A25: Total inflows | B25: =SUM(D25:CU25) | D25: =IF(D$4>T_End,0,D23+D24) | E25: =IF(E$4>T_End,0,E23+E24) | F25: =IF(F$4>T_End,0,F23+F24) | G25: =IF(G$4>T_End,0,G23+G24) | H25: =IF(H$4>T_End,0,H23+H24) | I25: =IF(I$4>T_End,0,I23+I24) | J25: =IF(J$4>T_End,0,J23+J24) | K25: =IF(K$4>T_End,0,K23+K24) | ... CU25: =IF(CU$4>T_End,0,CU23+CU24)
A26: Unlevered cash flow | B26: =SUM(D26:CU26) | D26: =D25-D22 | E26: =E25-E22 | F26: =F25-F22 | G26: =G25-G22 | H26: =H25-H22 | I26: =I25-I22 | J26: =J25-J22 | K26: =K25-K22 | ... CU26: =CU25-CU22
A27: Cumulative unlevered cash flow | D27: =D26 | E27: =E26+D27 | F27: =F26+E27 | G27: =G26+F27 | H27: =H26+G27 | I27: =I26+H27 | J27: =J26+I27 | K27: =K26+J27 | L27: =L26+K27 | ... CU27: =CU26+CT27
A28: Financing
A29: Senior debt: opening balance | D29: =0 | E29: =D56 | F29: =E56 | G29: =F56 | H29: =G56 | I29: =H56 | J29: =I56 | K29: =J56 | L29: =K56 | ... CU29: =CT56
A30: Senior interest | B30: =SUM(D30:CU30) | D30: =D29*F_SeniorRate/12 | E30: =E29*F_SeniorRate/12 | F30: =F29*F_SeniorRate/12 | G30: =G29*F_SeniorRate/12 | H30: =H29*F_SeniorRate/12 | I30: =I29*F_SeniorRate/12 | J30: =J29*F_SeniorRate/12 | K30: =K29*F_SeniorRate/12 | ... CU30: =CU29*F_SeniorRate/12
A31: Mezzanine: opening balance | D31: =0 | E31: =D57 | F31: =E57 | G31: =F57 | H31: =G57 | I31: =H57 | J31: =I57 | K31: =J57 | L31: =K57 | ... CU31: =CT57
A32: Mezzanine interest | B32: =SUM(D32:CU32) | D32: =D31*N(in_fin_mezz_rate_pct)/12 | E32: =E31*N(in_fin_mezz_rate_pct)/12 | F32: =F31*N(in_fin_mezz_rate_pct)/12 | G32: =G31*N(in_fin_mezz_rate_pct)/12 | H32: =H31*N(in_fin_mezz_rate_pct)/12 | I32: =I31*N(in_fin_mezz_rate_pct)/12 | J32: =J31*N(in_fin_mezz_rate_pct)/12 | K32: =K31*N(in_fin_mezz_rate_pct)/12 | ... CU32: =CU31*N(in_fin_mezz_rate_pct)/12
A33: Loan fees (commitment on undrawn + origination) | B33: =SUM(D33:CU33) | D33: =IF(AND(D$4>=T_ConStart,D$4<=T_Delivery,F_SeniorCommit>0),MAX(F_SeniorCommit-D29,0)*in_fin_commitment_fee_pct/12,0)+IF(AND(D$4=T_ConStart,F_SeniorCommit>0),F_SeniorCommit*in_fin_origination_fee_pct,0) | E33: =IF(AND(E$4>=T_ConStart,E$4<=T_Delivery,F_SeniorCommit>0),MAX(F_SeniorCommit-E29,0)*in_fin_commitment_fee_pct/12,0)+IF(AND(E$4=T_ConStart,F_SeniorCommit>0),F_SeniorCommit*in_fin_origination_fee_pct,0) | F33: =IF(AND(F$4>=T_ConStart,F$4<=T_Delivery,F_SeniorCommit>0),MAX(F_SeniorCommit-F29,0)*in_fin_commitment_fee_pct/12,0)+IF(AND(F$4=T_ConStart,F_SeniorCommit>0),F_SeniorCommit*in_fin_origination_fee_pct,0) | G33: =IF(AND(G$4>=T_ConStart,G$4<=T_Delivery,F_SeniorCommit>0),MAX(F_SeniorCommit-G29,0)*in_fin_commitment_fee_pct/12,0)+IF(AND(G$4=T_ConStart,F_SeniorCommit>0),F_SeniorCommit*in_fin_origination_fee_pct,0) | H33: =IF(AND(H$4>=T_ConStart,H$4<=T_Delivery,F_SeniorCommit>0),MAX(F_SeniorCommit-H29,0)*in_fin_commitment_fee_pct/12,0)+IF(AND(H$4=T_ConStart,F_SeniorCommit>0),F_SeniorCommit*in_fin_origination_fee_pct,0) | I33: =IF(AND(I$4>=T_ConStart,I$4<=T_Delivery,F_SeniorCommit>0),MAX(F_SeniorCommit-I29,0)*in_fin_commitment_fee_pct/12,0)+IF(AND(I$4=T_ConStart,F_SeniorCommit>0),F_SeniorCommit*in_fin_origination_fee_pct,0) | J33: =IF(AND(J$4>=T_ConStart,J$4<=T_Delivery,F_SeniorCommit>0),MAX(F_SeniorCommit-J29,0)*in_fin_commitment_fee_pct/12,0)+IF(AND(J$4=T_ConStart,F_SeniorCommit>0),F_SeniorCommit*in_fin_origination_fee_pct,0) | K33: =IF(AND(K$4>=T_ConStart,K$4<=T_Delivery,F_SeniorCommit>0),MAX(F_SeniorCommit-K29,0)*in_fin_commitment_fee_pct/12,0)+IF(AND(K$4=T_ConStart,F_SeniorCommit>0),F_SeniorCommit*in_fin_origination_fee_pct,0) | ... CU33: =IF(AND(CU$4>=T_ConStart,CU$4<=T_Delivery,F_SeniorCommit>0),MAX(F_SeniorCommit-CU29,0)*in_fin_commitment_fee_pct/12,0)+IF(AND(CU$4=T_ConStart,F_SeniorCommit>0),F_SeniorCommit*in_fin_origination_fee_pct,0)
A34: Senior interest capitalized | B34: =SUM(D34:CU34) | D34: =IF(AND(D$4<=T_Delivery,in_fin_interest_capitalized),MIN(D30,MAX(F_SeniorCommit-D29,0)),0) | E34: =IF(AND(E$4<=T_Delivery,in_fin_interest_capitalized),MIN(E30,MAX(F_SeniorCommit-E29,0)),0) | F34: =IF(AND(F$4<=T_Delivery,in_fin_interest_capitalized),MIN(F30,MAX(F_SeniorCommit-F29,0)),0) | G34: =IF(AND(G$4<=T_Delivery,in_fin_interest_capitalized),MIN(G30,MAX(F_SeniorCommit-G29,0)),0) | H34: =IF(AND(H$4<=T_Delivery,in_fin_interest_capitalized),MIN(H30,MAX(F_SeniorCommit-H29,0)),0) | I34: =IF(AND(I$4<=T_Delivery,in_fin_interest_capitalized),MIN(I30,MAX(F_SeniorCommit-I29,0)),0) | J34: =IF(AND(J$4<=T_Delivery,in_fin_interest_capitalized),MIN(J30,MAX(F_SeniorCommit-J29,0)),0) | K34: =IF(AND(K$4<=T_Delivery,in_fin_interest_capitalized),MIN(K30,MAX(F_SeniorCommit-K29,0)),0) | ... CU34: =IF(AND(CU$4<=T_Delivery,in_fin_interest_capitalized),MIN(CU30,MAX(F_SeniorCommit-CU29,0)),0)
A35: Mezzanine interest capitalized | B35: =SUM(D35:CU35) | D35: =IF(AND(D$4<=T_Delivery,in_fin_interest_capitalized),MIN(D32,MAX(F_MezzCommit-D31,0)),0) | E35: =IF(AND(E$4<=T_Delivery,in_fin_interest_capitalized),MIN(E32,MAX(F_MezzCommit-E31,0)),0) | F35: =IF(AND(F$4<=T_Delivery,in_fin_interest_capitalized),MIN(F32,MAX(F_MezzCommit-F31,0)),0) | G35: =IF(AND(G$4<=T_Delivery,in_fin_interest_capitalized),MIN(G32,MAX(F_MezzCommit-G31,0)),0) | H35: =IF(AND(H$4<=T_Delivery,in_fin_interest_capitalized),MIN(H32,MAX(F_MezzCommit-H31,0)),0) | I35: =IF(AND(I$4<=T_Delivery,in_fin_interest_capitalized),MIN(I32,MAX(F_MezzCommit-I31,0)),0) | J35: =IF(AND(J$4<=T_Delivery,in_fin_interest_capitalized),MIN(J32,MAX(F_MezzCommit-J31,0)),0) | K35: =IF(AND(K$4<=T_Delivery,in_fin_interest_capitalized),MIN(K32,MAX(F_MezzCommit-K31,0)),0) | ... CU35: =IF(AND(CU$4<=T_Delivery,in_fin_interest_capitalized),MIN(CU32,MAX(F_MezzCommit-CU31,0)),0)
A36: Interest paid in cash | B36: =SUM(D36:CU36) | D36: =D30+D32-D34-D35 | E36: =E30+E32-E34-E35 | F36: =F30+F32-F34-F35 | G36: =G30+G32-G34-G35 | H36: =H30+H32-H34-H35 | I36: =I30+I32-I34-I35 | J36: =J30+J32-J34-J35 | K36: =K30+K32-K34-K35 | ... CU36: =CU30+CU32-CU34-CU35
A37: Scheduled principal (rentals after delivery) | B37: =SUM(D37:CU37) | D37: =IF(AND(in_mode_sale=0,D$4>T_Delivery,D29>0,N(in_fin_amortization_years)>0),MIN(F_AmortPrincipal,D29),0) | E37: =IF(AND(in_mode_sale=0,E$4>T_Delivery,E29>0,N(in_fin_amortization_years)>0),MIN(F_AmortPrincipal,E29),0) | F37: =IF(AND(in_mode_sale=0,F$4>T_Delivery,F29>0,N(in_fin_amortization_years)>0),MIN(F_AmortPrincipal,F29),0) | G37: =IF(AND(in_mode_sale=0,G$4>T_Delivery,G29>0,N(in_fin_amortization_years)>0),MIN(F_AmortPrincipal,G29),0) | H37: =IF(AND(in_mode_sale=0,H$4>T_Delivery,H29>0,N(in_fin_amortization_years)>0),MIN(F_AmortPrincipal,H29),0) | I37: =IF(AND(in_mode_sale=0,I$4>T_Delivery,I29>0,N(in_fin_amortization_years)>0),MIN(F_AmortPrincipal,I29),0) | J37: =IF(AND(in_mode_sale=0,J$4>T_Delivery,J29>0,N(in_fin_amortization_years)>0),MIN(F_AmortPrincipal,J29),0) | K37: =IF(AND(in_mode_sale=0,K$4>T_Delivery,K29>0,N(in_fin_amortization_years)>0),MIN(F_AmortPrincipal,K29),0) | ... CU37: =IF(AND(in_mode_sale=0,CU$4>T_Delivery,CU29>0,N(in_fin_amortization_years)>0),MIN(F_AmortPrincipal,CU29),0)
A38: Funding need (+) / surplus (−) | D38: =D22-D25+D33+D36+D37 | E38: =E22-E25+E33+E36+E37 | F38: =F22-F25+F33+F36+F37 | G38: =G22-G25+G33+G36+G37 | H38: =H22-H25+H33+H36+H37 | I38: =I22-I25+I33+I36+I37 | J38: =J22-J25+J33+J36+J37 | K38: =K22-K25+K33+K36+K37 | ... CU38: =CU22-CU25+CU33+CU36+CU37
A39: Project cash reserve: opening | D39: =0 | E39: =D55 | F39: =E55 | G39: =F55 | H39: =G55 | I39: =H55 | J39: =I55 | K39: =J55 | L39: =K55 | ... CU39: =CT55
A40: Deficit paid from reserve | B40: =SUM(D40:CU40) | D40: =MIN(D39,MAX(D38,0)) | E40: =MIN(E39,MAX(E38,0)) | F40: =MIN(F39,MAX(F38,0)) | G40: =MIN(G39,MAX(G38,0)) | H40: =MIN(H39,MAX(H38,0)) | I40: =MIN(I39,MAX(I38,0)) | J40: =MIN(J39,MAX(J38,0)) | K40: =MIN(K39,MAX(K38,0)) | ... CU40: =MIN(CU39,MAX(CU38,0))
A41: Planned equity drawn | B41: =SUM(D41:CU41) | D41: =MIN(MAX(D38,0)-D40,MAX(F_EquityCap-0,0)) | E41: =MIN(MAX(E38,0)-E40,MAX(F_EquityCap-D42,0)) | F41: =MIN(MAX(F38,0)-F40,MAX(F_EquityCap-E42,0)) | G41: =MIN(MAX(G38,0)-G40,MAX(F_EquityCap-F42,0)) | H41: =MIN(MAX(H38,0)-H40,MAX(F_EquityCap-G42,0)) | I41: =MIN(MAX(I38,0)-I40,MAX(F_EquityCap-H42,0)) | J41: =MIN(MAX(J38,0)-J40,MAX(F_EquityCap-I42,0)) | K41: =MIN(MAX(K38,0)-K40,MAX(F_EquityCap-J42,0)) | L41: =MIN(MAX(L38,0)-L40,MAX(F_EquityCap-K42,0)) | ... CU41: =MIN(MAX(CU38,0)-CU40,MAX(F_EquityCap-CT42,0))
A42: Cumulative planned equity | D42: =D41 | E42: =E41+D42 | F42: =F41+E42 | G42: =G41+F42 | H42: =H41+G42 | I42: =I41+H42 | J42: =J41+I42 | K42: =K41+J42 | L42: =L41+K42 | ... CU42: =CU41+CT42
A43: Mezzanine drawn | B43: =SUM(D43:CU43) | D43: =MIN(MAX(D38,0)-D40-D41,MAX(F_MezzCommit-D31-D35,0)) | E43: =MIN(MAX(E38,0)-E40-E41,MAX(F_MezzCommit-E31-E35,0)) | F43: =MIN(MAX(F38,0)-F40-F41,MAX(F_MezzCommit-F31-F35,0)) | G43: =MIN(MAX(G38,0)-G40-G41,MAX(F_MezzCommit-G31-G35,0)) | H43: =MIN(MAX(H38,0)-H40-H41,MAX(F_MezzCommit-H31-H35,0)) | I43: =MIN(MAX(I38,0)-I40-I41,MAX(F_MezzCommit-I31-I35,0)) | J43: =MIN(MAX(J38,0)-J40-J41,MAX(F_MezzCommit-J31-J35,0)) | K43: =MIN(MAX(K38,0)-K40-K41,MAX(F_MezzCommit-K31-K35,0)) | ... CU43: =MIN(MAX(CU38,0)-CU40-CU41,MAX(F_MezzCommit-CU31-CU35,0))
A44: Senior debt drawn | B44: =SUM(D44:CU44) | D44: =MIN(MAX(D38,0)-D40-D41-D43,MAX(F_SeniorCommit-D29-D34,0)) | E44: =MIN(MAX(E38,0)-E40-E41-E43,MAX(F_SeniorCommit-E29-E34,0)) | F44: =MIN(MAX(F38,0)-F40-F41-F43,MAX(F_SeniorCommit-F29-F34,0)) | G44: =MIN(MAX(G38,0)-G40-G41-G43,MAX(F_SeniorCommit-G29-G34,0)) | H44: =MIN(MAX(H38,0)-H40-H41-H43,MAX(F_SeniorCommit-H29-H34,0)) | I44: =MIN(MAX(I38,0)-I40-I41-I43,MAX(F_SeniorCommit-I29-I34,0)) | J44: =MIN(MAX(J38,0)-J40-J41-J43,MAX(F_SeniorCommit-J29-J34,0)) | K44: =MIN(MAX(K38,0)-K40-K41-K43,MAX(F_SeniorCommit-K29-K34,0)) | ... CU44: =MIN(MAX(CU38,0)-CU40-CU41-CU43,MAX(F_SeniorCommit-CU29-CU34,0))
A45: Funding gap (additional equity required) | B45: =SUM(D45:CU45) | D45: =MAX(MAX(D38,0)-D40-D41-D43-D44,0) | E45: =MAX(MAX(E38,0)-E40-E41-E43-E44,0) | F45: =MAX(MAX(F38,0)-F40-F41-F43-F44,0) | G45: =MAX(MAX(G38,0)-G40-G41-G43-G44,0) | H45: =MAX(MAX(H38,0)-H40-H41-H43-H44,0) | I45: =MAX(MAX(I38,0)-I40-I41-I43-I44,0) | J45: =MAX(MAX(J38,0)-J40-J41-J43-J44,0) | K45: =MAX(MAX(K38,0)-K40-K41-K43-K44,0) | ... CU45: =MAX(MAX(CU38,0)-CU40-CU41-CU43-CU44,0)
A46: Surplus cash | D46: =MAX(-D38,0) | E46: =MAX(-E38,0) | F46: =MAX(-F38,0) | G46: =MAX(-G38,0) | H46: =MAX(-H38,0) | I46: =MAX(-I38,0) | J46: =MAX(-J38,0) | K46: =MAX(-K38,0) | ... CU46: =MAX(-CU38,0)
A47: Cash swept to debt | D47: =IF(D18=1,IF(D17=1,D46,IF(in_mode_sale=0,0,D46*in_fin_sweep_pct)),0) | E47: =IF(E18=1,IF(E17=1,E46,IF(in_mode_sale=0,0,E46*in_fin_sweep_pct)),0) | F47: =IF(F18=1,IF(F17=1,F46,IF(in_mode_sale=0,0,F46*in_fin_sweep_pct)),0) | G47: =IF(G18=1,IF(G17=1,G46,IF(in_mode_sale=0,0,G46*in_fin_sweep_pct)),0) | H47: =IF(H18=1,IF(H17=1,H46,IF(in_mode_sale=0,0,H46*in_fin_sweep_pct)),0) | I47: =IF(I18=1,IF(I17=1,I46,IF(in_mode_sale=0,0,I46*in_fin_sweep_pct)),0) | J47: =IF(J18=1,IF(J17=1,J46,IF(in_mode_sale=0,0,J46*in_fin_sweep_pct)),0) | K47: =IF(K18=1,IF(K17=1,K46,IF(in_mode_sale=0,0,K46*in_fin_sweep_pct)),0) | ... CU47: =IF(CU18=1,IF(CU17=1,CU46,IF(in_mode_sale=0,0,CU46*in_fin_sweep_pct)),0)
A48: Senior balance before repayment | D48: =D29+D34+D44-D37 | E48: =E29+E34+E44-E37 | F48: =F29+F34+F44-F37 | G48: =G29+G34+G44-G37 | H48: =H29+H34+H44-H37 | I48: =I29+I34+I44-I37 | J48: =J29+J34+J44-J37 | K48: =K29+K34+K44-K37 | ... CU48: =CU29+CU34+CU44-CU37
A49: Senior repayment from sweep | B49: =SUM(D49:CU49) | D49: =MIN(D47,D48) | E49: =MIN(E47,E48) | F49: =MIN(F47,F48) | G49: =MIN(G47,G48) | H49: =MIN(H47,H48) | I49: =MIN(I47,I48) | J49: =MIN(J47,J48) | K49: =MIN(K47,K48) | ... CU49: =MIN(CU47,CU48)
A50: Mezzanine balance before repayment | D50: =D31+D35+D43 | E50: =E31+E35+E43 | F50: =F31+F35+F43 | G50: =G31+G35+G43 | H50: =H31+H35+H43 | I50: =I31+I35+I43 | J50: =J31+J35+J43 | K50: =K31+K35+K43 | ... CU50: =CU31+CU35+CU43
A51: Mezzanine repayment from sweep | B51: =SUM(D51:CU51) | D51: =MIN(D47-D49,D50) | E51: =MIN(E47-E49,E50) | F51: =MIN(F47-F49,F50) | G51: =MIN(G47-G49,G50) | H51: =MIN(H47-H49,H50) | I51: =MIN(I47-I49,I50) | J51: =MIN(J47-J49,J50) | K51: =MIN(K47-K49,K50) | ... CU51: =MIN(CU47-CU49,CU50)
A52: Cash available to equity | D52: =IF(AND(D18=1,D46>0),D46-D49-D51+D39,0) | E52: =IF(AND(E18=1,E46>0),E46-E49-E51+E39,0) | F52: =IF(AND(F18=1,F46>0),F46-F49-F51+F39,0) | G52: =IF(AND(G18=1,G46>0),G46-G49-G51+G39,0) | H52: =IF(AND(H18=1,H46>0),H46-H49-H51+H39,0) | I52: =IF(AND(I18=1,I46>0),I46-I49-I51+I39,0) | J52: =IF(AND(J18=1,J46>0),J46-J49-J51+J39,0) | K52: =IF(AND(K18=1,K46>0),K46-K49-K51+K39,0) | ... CU52: =IF(AND(CU18=1,CU46>0),CU46-CU49-CU51+CU39,0)
A53: Final repayment of remaining debt | B53: =SUM(D53:CU53) | D53: =IF(D17=1,D48-D49+D50-D51,0) | E53: =IF(E17=1,E48-E49+E50-E51,0) | F53: =IF(F17=1,F48-F49+F50-F51,0) | G53: =IF(G17=1,G48-G49+G50-G51,0) | H53: =IF(H17=1,H48-H49+H50-H51,0) | I53: =IF(I17=1,I48-I49+I50-I51,0) | J53: =IF(J17=1,J48-J49+J50-J51,0) | K53: =IF(K17=1,K48-K49+K50-K51,0) | ... CU53: =IF(CU17=1,CU48-CU49+CU50-CU51,0)
A54: Final repayment shortfall (equity) | B54: =SUM(D54:CU54) | D54: =MAX(D53-D52,0) | E54: =MAX(E53-E52,0) | F54: =MAX(F53-F52,0) | G54: =MAX(G53-G52,0) | H54: =MAX(H53-H52,0) | I54: =MAX(I53-I52,0) | J54: =MAX(J53-J52,0) | K54: =MAX(K53-K52,0) | ... CU54: =MAX(CU53-CU52,0)
A55: Project cash reserve: closing | D55: =IF(D46>0,IF(D18=1,0,D39+D46),D39-D40) | E55: =IF(E46>0,IF(E18=1,0,E39+E46),E39-E40) | F55: =IF(F46>0,IF(F18=1,0,F39+F46),F39-F40) | G55: =IF(G46>0,IF(G18=1,0,G39+G46),G39-G40) | H55: =IF(H46>0,IF(H18=1,0,H39+H46),H39-H40) | I55: =IF(I46>0,IF(I18=1,0,I39+I46),I39-I40) | J55: =IF(J46>0,IF(J18=1,0,J39+J46),J39-J40) | K55: =IF(K46>0,IF(K18=1,0,K39+K46),K39-K40) | ... CU55: =IF(CU46>0,IF(CU18=1,0,CU39+CU46),CU39-CU40)
A56: Senior debt: closing balance | D56: =IF(D17=1,0,D48-D49) | E56: =IF(E17=1,0,E48-E49) | F56: =IF(F17=1,0,F48-F49) | G56: =IF(G17=1,0,G48-G49) | H56: =IF(H17=1,0,H48-H49) | I56: =IF(I17=1,0,I48-I49) | J56: =IF(J17=1,0,J48-J49) | K56: =IF(K17=1,0,K48-K49) | ... CU56: =IF(CU17=1,0,CU48-CU49)
A57: Mezzanine: closing balance | D57: =IF(D17=1,0,D50-D51) | E57: =IF(E17=1,0,E50-E51) | F57: =IF(F17=1,0,F50-F51) | G57: =IF(G17=1,0,G50-G51) | H57: =IF(H17=1,0,H50-H51) | I57: =IF(I17=1,0,I50-I51) | J57: =IF(J17=1,0,J50-J51) | K57: =IF(K17=1,0,K50-K51) | ... CU57: =IF(CU17=1,0,CU50-CU51)
A58: Debt service paid in cash (interest + principal) | B58: =SUM(D58:CU58) | D58: =D36+D37 | E58: =E36+E37 | F58: =F36+F37 | G58: =G36+G37 | H58: =H36+H37 | I58: =I36+I37 | J58: =J36+J37 | K58: =K36+K37 | ... CU58: =CU36+CU37
A59: Equity
A60: Equity contributions | B60: =SUM(D60:CU60) | D60: =D41+D45+D54 | E60: =E41+E45+E54 | F60: =F41+F45+F54 | G60: =G41+G45+G54 | H60: =H41+H45+H54 | I60: =I41+I45+I54 | J60: =J41+J45+J54 | K60: =K41+K45+K54 | ... CU60: =CU41+CU45+CU54
A61: Equity distributions | B61: =SUM(D61:CU61) | D61: =MAX(D52-IF(D17=1,D53,0),0) | E61: =MAX(E52-IF(E17=1,E53,0),0) | F61: =MAX(F52-IF(F17=1,F53,0),0) | G61: =MAX(G52-IF(G17=1,G53,0),0) | H61: =MAX(H52-IF(H17=1,H53,0),0) | I61: =MAX(I52-IF(I17=1,I53,0),0) | J61: =MAX(J52-IF(J17=1,J53,0),0) | K61: =MAX(K52-IF(K17=1,K53,0),0) | ... CU61: =MAX(CU52-IF(CU17=1,CU53,0),0)
A62: Levered (equity) cash flow | B62: =SUM(D62:CU62) | D62: =D61-D60 | E62: =E61-E60 | F62: =F61-F60 | G62: =G61-G60 | H62: =H61-H60 | I62: =I61-I60 | J62: =J61-J60 | K62: =K61-K60 | ... CU62: =CU61-CU60
A63: Cumulative net equity invested | D63: =D60-D61 | E63: =E60-E61+D63 | F63: =F60-F61+E63 | G63: =G60-G61+F63 | H63: =H60-H61+G63 | I63: =I60-I61+H63 | J63: =J60-J61+I63 | K63: =K60-K61+J63 | L63: =L60-L61+K63 | ... CU63: =CU60-CU61+CT63

Sheet Waterfall
A1: Equity waterfall
A2: Return of capital → preferred return (compounded monthly) → sponsor promote; pari passu contributions
A4: Month | B4: Total | C4: Unit / note | D4: 0 | E4: =D4+1 | F4: =E4+1 | G4: =F4+1 | H4: =G4+1 | I4: =H4+1 | J4: =I4+1 | K4: =J4+1 | L4: =K4+1 | ... CU4: =CT4+1
A5: Sponsor share of equity | B5: =in_fin_sponsor_equity_share_pct
A6: Monthly preferred return | B6: =(1+in_fin_pref_return_pct)^(1/12)-1
A7: Sponsor promote above pref | B7: =in_fin_promote_pct
A10: Equity contributions | B10: =SUM(D10:CU10) | D10: ='Cash Flow'!D60 | E10: ='Cash Flow'!E60 | F10: ='Cash Flow'!F60 | G10: ='Cash Flow'!G60 | H10: ='Cash Flow'!H60 | I10: ='Cash Flow'!I60 | J10: ='Cash Flow'!J60 | K10: ='Cash Flow'!K60 | ... CU10: ='Cash Flow'!CU60
A11: Equity distributions | B11: =SUM(D11:CU11) | D11: ='Cash Flow'!D61 | E11: ='Cash Flow'!E61 | F11: ='Cash Flow'!F61 | G11: ='Cash Flow'!G61 | H11: ='Cash Flow'!H61 | I11: ='Cash Flow'!I61 | J11: ='Cash Flow'!J61 | K11: ='Cash Flow'!K61 | ... CU11: ='Cash Flow'!CU61
A12: Unreturned capital: opening | D12: =0 | E12: =D18 | F12: =E18 | G12: =F18 | H12: =G18 | I12: =H18 | J12: =I18 | K12: =J18 | L12: =K18 | ... CU12: =CT18
A13: Accrued preferred return: opening | D13: =0 | E13: =D19 | F13: =E19 | G13: =F19 | H13: =G19 | I13: =H19 | J13: =I19 | K13: =J19 | L13: =K19 | ... CU13: =CT19
A14: Preferred return accrued | B14: =SUM(D14:CU14) | D14: =(D12+D13)*W_rp | E14: =(E12+E13)*W_rp | F14: =(F12+F13)*W_rp | G14: =(G12+G13)*W_rp | H14: =(H12+H13)*W_rp | I14: =(I12+I13)*W_rp | J14: =(J12+J13)*W_rp | K14: =(K12+K13)*W_rp | ... CU14: =(CU12+CU13)*W_rp
A15: Tier 1: return of capital | B15: =SUM(D15:CU15) | D15: =MIN(D11,D12+D10) | E15: =MIN(E11,E12+E10) | F15: =MIN(F11,F12+F10) | G15: =MIN(G11,G12+G10) | H15: =MIN(H11,H12+H10) | I15: =MIN(I11,I12+I10) | J15: =MIN(J11,J12+J10) | K15: =MIN(K11,K12+K10) | ... CU15: =MIN(CU11,CU12+CU10)
A16: Tier 2: preferred return | B16: =SUM(D16:CU16) | D16: =MIN(D11-D15,D13+D14) | E16: =MIN(E11-E15,E13+E14) | F16: =MIN(F11-F15,F13+F14) | G16: =MIN(G11-G15,G13+G14) | H16: =MIN(H11-H15,H13+H14) | I16: =MIN(I11-I15,I13+I14) | J16: =MIN(J11-J15,J13+J14) | K16: =MIN(K11-K15,K13+K14) | ... CU16: =MIN(CU11-CU15,CU13+CU14)
A17: Tier 3: residual | B17: =SUM(D17:CU17) | D17: =D11-D15-D16 | E17: =E11-E15-E16 | F17: =F11-F15-F16 | G17: =G11-G15-G16 | H17: =H11-H15-H16 | I17: =I11-I15-I16 | J17: =J11-J15-J16 | K17: =K11-K15-K16 | ... CU17: =CU11-CU15-CU16
A18: Unreturned capital: closing | D18: =D12+D10-D15 | E18: =E12+E10-E15 | F18: =F12+F10-F15 | G18: =G12+G10-G15 | H18: =H12+H10-H15 | I18: =I12+I10-I15 | J18: =J12+J10-J15 | K18: =K12+K10-K15 | ... CU18: =CU12+CU10-CU15
A19: Accrued preferred return: closing | D19: =D13+D14-D16 | E19: =E13+E14-E16 | F19: =F13+F14-F16 | G19: =G13+G14-G16 | H19: =H13+H14-H16 | I19: =I13+I14-I16 | J19: =J13+J14-J16 | K19: =K13+K14-K16 | ... CU19: =CU13+CU14-CU16
A20: Investor cash flow | B20: =SUM(D20:CU20) | D20: =(-D10+D15+D16+D17*(1-W_promote))*(1-W_s) | E20: =(-E10+E15+E16+E17*(1-W_promote))*(1-W_s) | F20: =(-F10+F15+F16+F17*(1-W_promote))*(1-W_s) | G20: =(-G10+G15+G16+G17*(1-W_promote))*(1-W_s) | H20: =(-H10+H15+H16+H17*(1-W_promote))*(1-W_s) | I20: =(-I10+I15+I16+I17*(1-W_promote))*(1-W_s) | J20: =(-J10+J15+J16+J17*(1-W_promote))*(1-W_s) | K20: =(-K10+K15+K16+K17*(1-W_promote))*(1-W_s) | ... CU20: =(-CU10+CU15+CU16+CU17*(1-W_promote))*(1-W_s)
A21: Sponsor cash flow | B21: =SUM(D21:CU21) | D21: =(-D10+D15+D16+D17*(1-W_promote))*W_s+D17*W_promote | E21: =(-E10+E15+E16+E17*(1-W_promote))*W_s+E17*W_promote | F21: =(-F10+F15+F16+F17*(1-W_promote))*W_s+F17*W_promote | G21: =(-G10+G15+G16+G17*(1-W_promote))*W_s+G17*W_promote | H21: =(-H10+H15+H16+H17*(1-W_promote))*W_s+H17*W_promote | I21: =(-I10+I15+I16+I17*(1-W_promote))*W_s+I17*W_promote | J21: =(-J10+J15+J16+J17*(1-W_promote))*W_s+J17*W_promote | K21: =(-K10+K15+K16+K17*(1-W_promote))*W_s+K17*W_promote | ... CU21: =(-CU10+CU15+CU16+CU17*(1-W_promote))*W_s+CU17*W_promote

Sheet Budget
A1: Development budget
A2: MXN. Every line links to the monthly schedules; per m² of total GBA and per unit
A4: Line item | B4: Amount (MXN) | C4: Per m² GBA | D4: Per unit | E4: % of total | F4: Basis
A5: Acquisition
A6: Land / property price | B6: =SUM(M_land) | C6: =IF((D_GBA+D_Below)>0,B6/(D_GBA+D_Below),0) | D6: =IF(D_Units>0,B6/D_Units,0) | E6: =IF(TotalCost<>0,B6/TotalCost,0) | F6: Land payment schedule
A7: Taxes, notary, brokerage & due diligence | B7: =SUM(M_acq) | C7: =IF((D_GBA+D_Below)>0,B7/(D_GBA+D_Below),0) | D7: =IF(D_Units>0,B7/D_Units,0) | E7: =IF(TotalCost<>0,B7/TotalCost,0) | F7: % of land price + fixed
A8: Construction
A9: Hard costs (escalated, incl. sustainability capex) | B9: =SUM(M_hard) | C9: =IF((D_GBA+D_Below)>0,B9/(D_GBA+D_Below),0) | D9: =IF(D_Units>0,B9/D_Units,0) | E9: =IF(TotalCost<>0,B9/TotalCost,0) | F9: per m² × GBA, S-curve, escalation
A10: Soft costs | B10: =SUM(M_soft) | C10: =IF((D_GBA+D_Below)>0,B10/(D_GBA+D_Below),0) | D10: =IF(D_Units>0,B10/D_Units,0) | E10: =IF(TotalCost<>0,B10/TotalCost,0) | F10: % of hard-cost base
A11: Contingency | B11: =SUM(M_cont) | C11: =IF((D_GBA+D_Below)>0,B11/(D_GBA+D_Below),0) | D11: =IF(D_Units>0,B11/D_Units,0) | E11: =IF(TotalCost<>0,B11/TotalCost,0) | F11: % of hard + soft
A12: Developer fee | B12: =SUM(M_fee) | C12: =IF((D_GBA+D_Below)>0,B12/(D_GBA+D_Below),0) | D12: =IF(D_Units>0,B12/D_Units,0) | E12: =IF(TotalCost<>0,B12/TotalCost,0) | F12: % of hard + soft
A13: User-defined variable costs | B13: =SUM(M_cv) | C13: =IF((D_GBA+D_Below)>0,B13/(D_GBA+D_Below),0) | D13: =IF(D_Units>0,B13/D_Units,0) | E13: =IF(TotalCost<>0,B13/TotalCost,0) | F13: Assumptions → user-defined variables
A14: Custom one-off costs | B14: =SUM(M_cflow) | C14: =IF((D_GBA+D_Below)>0,B14/(D_GBA+D_Below),0) | D14: =IF(D_Units>0,B14/D_Units,0) | E14: =IF(TotalCost<>0,B14/TotalCost,0) | F14: Assumptions → custom cash flows
A15: Sales & marketing
A16: Sales costs (commissions, marketing, % of collections) | B16: =IF(in_mode_sale=1,SUM(M_SalesCost),0) | C16: =IF((D_GBA+D_Below)>0,B16/(D_GBA+D_Below),0) | D16: =IF(D_Units>0,B16/D_Units,0) | E16: =IF(TotalCost<>0,B16/TotalCost,0) | F16: % of contract value / revenue
A17: Financing
A18: Interest and loan fees | B18: =FinCost | C18: =IF((D_GBA+D_Below)>0,B18/(D_GBA+D_Below),0) | D18: =IF(D_Units>0,B18/D_Units,0) | E18: =IF(TotalCost<>0,B18/TotalCost,0) | F18: On actual monthly balances
A19: Total cost incl. financing | B19: =SUM(B5:B18) | F19: Check vs Cash Flow: | G19: =ROUND(B19-TotalCost,0)
A22: Hard-cost breakdown by category (today's prices, above ground)
A23: =Assumptions!A123 | B23: =C_HardAbove*Assumptions!B123
A24: =Assumptions!A124 | B24: =C_HardAbove*Assumptions!B124
A25: =Assumptions!A125 | B25: =C_HardAbove*Assumptions!B125
A26: =Assumptions!A126 | B26: =C_HardAbove*Assumptions!B126
A27: =Assumptions!A127 | B27: =C_HardAbove*Assumptions!B127
A28: =Assumptions!A128 | B28: =C_HardAbove*Assumptions!B128
A29: =Assumptions!A129 | B29: =C_HardAbove*Assumptions!B129
A30: =Assumptions!A130 | B30: =C_HardAbove*Assumptions!B130
A31: =Assumptions!A131 | B31: =C_HardAbove*Assumptions!B131
A32: =Assumptions!A132 | B32: =C_HardAbove*Assumptions!B132

Sheet Sensitivity
A1: Sensitivity & scenarios (TerraMind engine snapshot)
A2: Values computed by TerraMind's engine at export. Re-export after major changes.
A4: Scenario | B4: Equity IRR | C4: Profit | D4: Net margin | E4: MOIC | F4: Peak equity
A5: Base | B5: 0.24913765 | C5: 2.812391e+08 | D5: 0.27134024 | E5: 1.6770593 | F5: 4.1538324e+08
A6: Upside | B6: 0.31765558 | C6: 3.6525302e+08 | D6: 0.3313986 | E6: 1.901199 | F6: 4.0529675e+08
A7: Downside | B7: 0.11492445 | C7: 1.544408e+08 | D7: 0.16172854 | E7: 1.3507836 | F7: 4.4027372e+08
A10: Equity IRR sensitivity (tornado)
A11: Driver | B11: Low | C11: High
A12: Sale price ±10% | B12: 0.16914635 | C12: 0.32243862
A13: Construction ±6 months | B13: 0.3142738 | C13: 0.20214037
A14: Land price ±10% | B14: 0.28923525 | C14: 0.21305576
A15: Hard cost ±10% | B15: 0.28092274 | C15: 0.21753241
A16: Interest rate ±200 bp | B16: 0.25021282 | C16: 0.24807085
A17: Absorption ±25% | B17: 0.24651116 | C17: 0.24567495
A20: Equity IRR: Hard cost above ground (rows) × Base sale price (columns), % change
A21: Cost Δ \ Price Δ | B21: -0.15 | C21: -0.075 | D21: 0 | E21: 0.075 | F21: 0.15
A22: -0.15 | B22: 0.17694481 | C22: 0.23908484 | D22: 0.29690137 | E22: 0.35122838 | F22: 0.40258549
A23: -0.075 | B23: 0.15143982 | C23: 0.21442144 | D23: 0.27296363 | E23: 0.327886 | F23: 0.37975801
A24: 0 | B24: 0.12604016 | C24: 0.18986447 | D24: 0.24913765 | E24: 0.30466425 | F24: 0.35704661
A25: 0.075 | B25: 0.10074312 | C25: 0.1654237 | D25: 0.2254143 | E25: 0.28154443 | F25: 0.33445752
A26: 0.15 | B26: 0.075523684 | C26: 0.14110652 | D26: 0.20180771 | E26: 0.25853015 | F26: 0.31197717
